[{"y":2019,"m":0,"oil":25.16,"gas":12.38,"water":739.92},{"y":2019,"m":1,"oil":21.02,"gas":8.56,"water":481.62},{"y":2019,"m":2,"oil":27.56,"gas":11.7,"water":638.4},{"y":2019,"m":3,"oil":22.45,"gas":10.74,"water":510.35},{"y":2019,"m":4,"oil":0,"gas":0,"water":0},{"y":2019,"m":5,"oil":0,"gas":0,"water":0},{"y":2019,"m":6,"oil":18.57,"gas":4.23,"water":440.23},{"y":2019,"m":7,"oil":17.93,"gas":8.21,"water":751.16},{"y":2019,"m":8,"oil":12.22,"gas":9.4,"water":868.35},{"y":2019,"m":9,"oil":27.59,"gas":12.97,"water":905.77},{"y":2019,"m":10,"oil":31.38,"gas":12.7,"water":850.77},{"y":2019,"m":11,"oil":43.11,"gas":11.94,"water":794.76},{"y":2020,"m":0,"oil":44.72,"gas":11.24,"water":732.98},{"y":2020,"m":1,"oil":43,"gas":8.16,"water":646.9},{"y":2020,"m":2,"oil":38.65,"gas":8.94,"water":622.63},{"y":2020,"m":3,"oil":27.27,"gas":8.22,"water":648.46},{"y":2020,"m":4,"oil":43.58,"gas":8.83,"water":685.81},{"y":2020,"m":5,"oil":41.59,"gas":7.82,"water":588.19},{"y":2020,"m":6,"oil":43.56,"gas":9.26,"water":556.05},{"y":2020,"m":7,"oil":57.22,"gas":8.14,"water":518.28},{"y":2020,"m":8,"oil":63.68,"gas":7.26,"water":594.82},{"y":2020,"m":9,"oil":57.54,"gas":8.69,"water":564.26},{"y":2020,"m":10,"oil":49.19,"gas":6.51,"water":584.7},{"y":2020,"m":11,"oil":51.15,"gas":5.98,"water":583.99},{"y":2021,"m":0,"oil":55.56,"gas":7.58,"water":599.28},{"y":2021,"m":1,"oil":40.27,"gas":7.9,"water":454.7},{"y":2021,"m":2,"oil":28.92,"gas":13.3,"water":467.61},{"y":2021,"m":3,"oil":27.42,"gas":9.8,"water":424.08},{"y":2021,"m":4,"oil":29.21,"gas":9.8,"water":473.36},{"y":2021,"m":5,"oil":27.18,"gas":8.71,"water":513.93},{"y":2021,"m":6,"oil":28.44,"gas":8.99,"water":504.66},{"y":2021,"m":7,"oil":29.23,"gas":8.57,"water":588.6},{"y":2021,"m":8,"oil":21.83,"gas":6.45,"water":489.42},{"y":2021,"m":9,"oil":24.72,"gas":7.26,"water":556.39},{"y":2021,"m":10,"oil":24,"gas":7,"water":557.41},{"y":2021,"m":11,"oil":33.42,"gas":8.05,"water":644.69},{"y":2022,"m":0,"oil":37.75,"gas":7.83,"water":700.55},{"y":2022,"m":1,"oil":33.78,"gas":9.88,"water":641.96},{"y":2022,"m":2,"oil":29.12,"gas":6.11,"water":608.55},{"y":2022,"m":3,"oil":29.66,"gas":3.65,"water":620.64},{"y":2022,"m":4,"oil":24.1,"gas":3.65,"water":478.14},{"y":2022,"m":5,"oil":29.15,"gas":5.44,"water":590.5},{"y":2022,"m":6,"oil":23.57,"gas":8.6,"water":666.81},{"y":2022,"m":7,"oil":20.81,"gas":7.81,"water":677.44},{"y":2022,"m":8,"oil":15.55,"gas":6.1,"water":428.94},{"y":2022,"m":9,"oil":2.5,"gas":1.18,"water":63.91},{"y":2022,"m":10,"oil":13.57,"gas":6.88,"water":349.63},{"y":2022,"m":11,"oil":12.07,"gas":7.12,"water":442.32},{"y":2023,"m":0,"oil":10.15,"gas":12.49,"water":446.98},{"y":2023,"m":1,"oil":9.2,"gas":9.48,"water":400.37},{"y":2023,"m":2,"oil":10.64,"gas":10.89,"water":424.64},{"y":2023,"m":3,"oil":17.79,"gas":7.5,"water":372.41},{"y":2023,"m":4,"oil":21.72,"gas":8.89,"water":400.46},{"y":2023,"m":5,"oil":22.81,"gas":7.73,"water":359.52},{"y":2023,"m":6,"oil":26.76,"gas":9.03,"water":384.07},{"y":2023,"m":7,"oil":25.4,"gas":5.25,"water":404.08},{"y":2023,"m":8,"oil":22.97,"gas":9.21,"water":403.58},{"y":2023,"m":9,"oil":23.22,"gas":9.67,"water":417.35},{"y":2023,"m":10,"oil":16.31,"gas":12.6,"water":428.79},{"y":2023,"m":11,"oil":16.57,"gas":11.67,"water":422.96},{"y":2024,"m":0,"oil":14.9,"gas":13.39,"water":376.73},{"y":2024,"m":1,"oil":13.93,"gas":13.34,"water":404.47},{"y":2024,"m":2,"oil":12.63,"gas":16.1,"water":404.22},{"y":2024,"m":3,"oil":11.62,"gas":15.92,"water":323.33},{"y":2024,"m":4,"oil":13.6,"gas":16.89,"water":348.96},{"y":2024,"m":5,"oil":19.44,"gas":18.89,"water":345.16},{"y":2024,"m":6,"oil":17.59,"gas":19.63,"water":333.47},{"y":2024,"m":7,"oil":20.27,"gas":20.31,"water":340.33},{"y":2024,"m":8,"oil":20.4,"gas":13.69,"water":354.72},{"y":2024,"m":9,"oil":19.82,"gas":13.32,"water":366.56},{"y":2024,"m":10,"oil":15.7,"gas":10.46,"water":348.73},{"y":2024,"m":11,"oil":13.68,"gas":11.24,"water":390.04},{"y":2025,"m":0,"oil":10.72,"gas":11.77,"water":383.47},{"y":2025,"m":1,"oil":10.94,"gas":7.57,"water":339.09},{"y":2025,"m":2,"oil":13.19,"gas":7.27,"water":419.89},{"y":2025,"m":3,"oil":11.95,"gas":9.37,"water":420.44},{"y":2025,"m":4,"oil":13.5,"gas":15.47,"water":441.27},{"y":2025,"m":5,"oil":12.25,"gas":12.99,"water":449.21},{"y":2025,"m":6,"oil":12.99,"gas":10.21,"water":447},{"y":2025,"m":7,"oil":12.33,"gas":6.85,"water":416.45},{"y":2025,"m":8,"oil":12.62,"gas":7.5,"water":415.68},{"y":2025,"m":9,"oil":12.33,"gas":3.11,"water":420.58},{"y":2025,"m":10,"oil":12.25,"gas":6.71,"water":430.76},{"y":2025,"m":11,"oil":10.52582,"gas":5.392531,"water":422.6792},{"y":2026,"m":0,"oil":10.46919,"gas":7.99162,"water":430.1458},{"y":2026,"m":1,"oil":10.63036,"gas":8.957278,"water":381.838},{"y":2026,"m":2,"oil":6.990568,"gas":9.090613,"water":447.2831},{"y":2026,"m":3,"oil":4.959181,"gas":8.016207,"water":419.8432}]