[{"y":2019,"m":0,"oil":64.27,"gas":0,"water":3257.45},{"y":2019,"m":1,"oil":82.11,"gas":0,"water":3852.2},{"y":2019,"m":2,"oil":117.6,"gas":0,"water":2879.85},{"y":2019,"m":3,"oil":51.38,"gas":0,"water":2682.35},{"y":2019,"m":4,"oil":38.28,"gas":0,"water":2775},{"y":2019,"m":5,"oil":59.7,"gas":0,"water":3084.81},{"y":2019,"m":6,"oil":65.17,"gas":0,"water":3408.62},{"y":2019,"m":7,"oil":67.67,"gas":0,"water":3532.92},{"y":2019,"m":8,"oil":65.33,"gas":0,"water":3403.58},{"y":2019,"m":9,"oil":63.53,"gas":0,"water":3282.14},{"y":2019,"m":10,"oil":62.14,"gas":0,"water":3141.69},{"y":2019,"m":11,"oil":48.1,"gas":0,"water":3329.93},{"y":2020,"m":0,"oil":33.8,"gas":0,"water":3374.62},{"y":2020,"m":1,"oil":36.01,"gas":0,"water":3645.16},{"y":2020,"m":2,"oil":38.55,"gas":0,"water":3964.4},{"y":2020,"m":3,"oil":34.04,"gas":0,"water":3519.24},{"y":2020,"m":4,"oil":38.24,"gas":0,"water":3949.86},{"y":2020,"m":5,"oil":36.31,"gas":0,"water":3754.8},{"y":2020,"m":6,"oil":35.87,"gas":0,"water":3780.45},{"y":2020,"m":7,"oil":37.01,"gas":0,"water":3879.05},{"y":2020,"m":8,"oil":37.56,"gas":0,"water":3923.04},{"y":2020,"m":9,"oil":38.29,"gas":0,"water":3999.15},{"y":2020,"m":10,"oil":36.62,"gas":0,"water":3920.28},{"y":2020,"m":11,"oil":36.33,"gas":0,"water":3974.79},{"y":2021,"m":0,"oil":37.31,"gas":0,"water":4040.5},{"y":2021,"m":1,"oil":57.47,"gas":0,"water":3614.66},{"y":2021,"m":2,"oil":96.84,"gas":0,"water":4292.97},{"y":2021,"m":3,"oil":93.42,"gas":0,"water":3917.16},{"y":2021,"m":4,"oil":42.6,"gas":0,"water":2174.1},{"y":2021,"m":5,"oil":44.84,"gas":0,"water":2393.62},{"y":2021,"m":6,"oil":70,"gas":0,"water":3335.28},{"y":2021,"m":7,"oil":70.69,"gas":0,"water":3014.3},{"y":2021,"m":8,"oil":65.88,"gas":0,"water":2764.58},{"y":2021,"m":9,"oil":63.54,"gas":0,"water":2838.71},{"y":2021,"m":10,"oil":52.26,"gas":0,"water":2704.49},{"y":2021,"m":11,"oil":52.77,"gas":0,"water":2697.53},{"y":2022,"m":0,"oil":49.91,"gas":0,"water":2758.23},{"y":2022,"m":1,"oil":36.31,"gas":0,"water":2441.87},{"y":2022,"m":2,"oil":55.03,"gas":0,"water":2723.13},{"y":2022,"m":3,"oil":47.68,"gas":0,"water":2360.39},{"y":2022,"m":4,"oil":51.91,"gas":0,"water":2580.73},{"y":2022,"m":5,"oil":52.96,"gas":0,"water":2671.47},{"y":2022,"m":6,"oil":63.72,"gas":0,"water":2630.36},{"y":2022,"m":7,"oil":0,"gas":0,"water":0},{"y":2022,"m":8,"oil":0,"gas":0,"water":0},{"y":2022,"m":9,"oil":22.72,"gas":0,"water":975.22},{"y":2022,"m":10,"oil":55.66,"gas":0,"water":2429.71},{"y":2022,"m":11,"oil":74.94,"gas":0,"water":3430.54},{"y":2023,"m":0,"oil":72.33,"gas":0,"water":3233.55},{"y":2023,"m":1,"oil":48.05,"gas":0,"water":2520.12},{"y":2023,"m":2,"oil":53.06,"gas":0,"water":2167.32},{"y":2023,"m":3,"oil":81.16,"gas":0,"water":2939.41},{"y":2023,"m":4,"oil":82.42,"gas":0,"water":2947.17},{"y":2023,"m":5,"oil":54.93,"gas":0,"water":3143.2},{"y":2023,"m":6,"oil":48.74,"gas":0,"water":2886.64},{"y":2023,"m":7,"oil":54.41,"gas":0,"water":3156.92},{"y":2023,"m":8,"oil":21.16,"gas":0,"water":1160.88},{"y":2023,"m":9,"oil":0,"gas":0,"water":0},{"y":2023,"m":10,"oil":0,"gas":0,"water":0},{"y":2023,"m":11,"oil":24.26,"gas":0,"water":906.86},{"y":2024,"m":0,"oil":92.13,"gas":0,"water":4820.98},{"y":2024,"m":1,"oil":69.81,"gas":0,"water":5025.82},{"y":2024,"m":2,"oil":72.6,"gas":0,"water":5526.06},{"y":2024,"m":3,"oil":83.61,"gas":0,"water":5136.27},{"y":2024,"m":4,"oil":99.22,"gas":0,"water":5369.9},{"y":2024,"m":5,"oil":53.69,"gas":0,"water":3371.8},{"y":2024,"m":6,"oil":43.03,"gas":0,"water":2350.73},{"y":2024,"m":7,"oil":74.16,"gas":0,"water":5513.48},{"y":2024,"m":8,"oil":67.99,"gas":0,"water":5322.28},{"y":2024,"m":9,"oil":59.75,"gas":0,"water":5642.86},{"y":2024,"m":10,"oil":42.209,"gas":0,"water":5135.141},{"y":2024,"m":11,"oil":46.578,"gas":0,"water":5548.15},{"y":2025,"m":0,"oil":44.64739,"gas":0,"water":4836.56237},{"y":2025,"m":1,"oil":20.89175,"gas":0,"water":2452.46928},{"y":2025,"m":2,"oil":0,"gas":0,"water":0},{"y":2025,"m":3,"oil":0,"gas":0,"water":0},{"y":2025,"m":4,"oil":0,"gas":0,"water":0},{"y":2025,"m":5,"oil":0.000834,"gas":0,"water":0.125347},{"y":2025,"m":6,"oil":0.000832,"gas":0,"water":0.127516},{"y":2025,"m":7,"oil":48.70647,"gas":0,"water":5160.397},{"y":2025,"m":8,"oil":50.19869,"gas":0,"water":5100.54},{"y":2025,"m":9,"oil":49.50133,"gas":0,"water":5308.157},{"y":2025,"m":10,"oil":45.55165,"gas":0,"water":4562.79},{"y":2025,"m":11,"oil":49.29246,"gas":0,"water":5142.493},{"y":2026,"m":0,"oil":44.88842,"gas":0,"water":5109.424},{"y":2026,"m":1,"oil":40.97185,"gas":0,"water":4724.351},{"y":2026,"m":2,"oil":46.86553,"gas":0,"water":5282.988},{"y":2026,"m":3,"oil":39.47313,"gas":0,"water":4809.016}]