[{"y":2019,"m":0,"oil":34.45,"gas":5.92,"water":2071.67},{"y":2019,"m":1,"oil":28.22,"gas":5.15,"water":1869.65},{"y":2019,"m":2,"oil":28.89,"gas":4.22,"water":2004.55},{"y":2019,"m":3,"oil":27.17,"gas":5.23,"water":1958.79},{"y":2019,"m":4,"oil":29.17,"gas":4.26,"water":2031.69},{"y":2019,"m":5,"oil":27.22,"gas":2.96,"water":1915.65},{"y":2019,"m":6,"oil":29,"gas":3.49,"water":2018.78},{"y":2019,"m":7,"oil":28.92,"gas":3.77,"water":2023.47},{"y":2019,"m":8,"oil":27.49,"gas":3.23,"water":1980.91},{"y":2019,"m":9,"oil":28.18,"gas":2.3,"water":1978.76},{"y":2019,"m":10,"oil":27.13,"gas":2.4,"water":1928.35},{"y":2019,"m":11,"oil":25.48,"gas":2.2,"water":1781.33},{"y":2020,"m":0,"oil":28.11,"gas":2.45,"water":1959.05},{"y":2020,"m":1,"oil":26.99,"gas":2.42,"water":1801.21},{"y":2020,"m":2,"oil":27.17,"gas":2.3,"water":1866.94},{"y":2020,"m":3,"oil":26.2,"gas":2.09,"water":1768.42},{"y":2020,"m":4,"oil":26.69,"gas":2.46,"water":2029.2},{"y":2020,"m":5,"oil":25.87,"gas":2.32,"water":1848.99},{"y":2020,"m":6,"oil":25.91,"gas":2.55,"water":2187.32},{"y":2020,"m":7,"oil":23.14,"gas":2.34,"water":1901.75},{"y":2020,"m":8,"oil":25.1,"gas":2.69,"water":2069.76},{"y":2020,"m":9,"oil":24.26,"gas":2.81,"water":2091.82},{"y":2020,"m":10,"oil":24.54,"gas":2.35,"water":1952.79},{"y":2020,"m":11,"oil":24.49,"gas":2.2,"water":1919.96},{"y":2021,"m":0,"oil":24.91,"gas":2.56,"water":1900.94},{"y":2021,"m":1,"oil":23.13,"gas":2.43,"water":1723.62},{"y":2021,"m":2,"oil":24.02,"gas":2.82,"water":1812.5},{"y":2021,"m":3,"oil":24.52,"gas":2.63,"water":1861.98},{"y":2021,"m":4,"oil":25.04,"gas":2.46,"water":1906.67},{"y":2021,"m":5,"oil":24.64,"gas":2.29,"water":1800.47},{"y":2021,"m":6,"oil":24.35,"gas":2.03,"water":1793.68},{"y":2021,"m":7,"oil":24.54,"gas":2.55,"water":1835.25},{"y":2021,"m":8,"oil":24.05,"gas":2.22,"water":1768.6},{"y":2021,"m":9,"oil":24.69,"gas":2.4,"water":1851.78},{"y":2021,"m":10,"oil":24.28,"gas":2.84,"water":1794.07},{"y":2021,"m":11,"oil":24.64,"gas":2.84,"water":1871.83},{"y":2022,"m":0,"oil":24.48,"gas":2.63,"water":1933.74},{"y":2022,"m":1,"oil":22.44,"gas":1.91,"water":1894.56},{"y":2022,"m":2,"oil":25.59,"gas":2.8,"water":2070.41},{"y":2022,"m":3,"oil":24.8,"gas":1.96,"water":2021.49},{"y":2022,"m":4,"oil":25.34,"gas":1.47,"water":1944.39},{"y":2022,"m":5,"oil":24.24,"gas":1.47,"water":1916.57},{"y":2022,"m":6,"oil":24.29,"gas":1.43,"water":1844.08},{"y":2022,"m":7,"oil":24,"gas":1.29,"water":1715.56},{"y":2022,"m":8,"oil":22.5,"gas":1.23,"water":1681.87},{"y":2022,"m":9,"oil":22.33,"gas":1.22,"water":1693.42},{"y":2022,"m":10,"oil":22.19,"gas":1.22,"water":1760.33},{"y":2022,"m":11,"oil":23.6,"gas":1.31,"water":1890.41},{"y":2023,"m":0,"oil":22.75,"gas":1.36,"water":1873.09},{"y":2023,"m":1,"oil":18.49,"gas":1.11,"water":1497.77},{"y":2023,"m":2,"oil":23.59,"gas":1.41,"water":1882.83},{"y":2023,"m":3,"oil":23.83,"gas":1.37,"water":1849.38},{"y":2023,"m":4,"oil":23.38,"gas":1.36,"water":1886.21},{"y":2023,"m":5,"oil":23.07,"gas":1.35,"water":1798.12},{"y":2023,"m":6,"oil":23.66,"gas":1.4,"water":1846.26},{"y":2023,"m":7,"oil":22.17,"gas":1.4,"water":1771.26},{"y":2023,"m":8,"oil":22.35,"gas":1.4,"water":2018.07},{"y":2023,"m":9,"oil":22.46,"gas":1.45,"water":2188.46},{"y":2023,"m":10,"oil":21.87,"gas":1.39,"water":2037.63},{"y":2023,"m":11,"oil":22.76,"gas":1.46,"water":2091.38},{"y":2024,"m":0,"oil":22.23,"gas":1.39,"water":2064.04},{"y":2024,"m":1,"oil":21.05,"gas":1.26,"water":1767.12},{"y":2024,"m":2,"oil":22.48,"gas":1.33,"water":1814.93},{"y":2024,"m":3,"oil":7.29,"gas":0.44,"water":582.69},{"y":2024,"m":4,"oil":0.51,"gas":0.03,"water":42.78},{"y":2024,"m":5,"oil":26.32,"gas":1.18,"water":2495.28},{"y":2024,"m":6,"oil":26.03,"gas":0.84,"water":2742.49},{"y":2024,"m":7,"oil":24.19,"gas":0.81,"water":2345.05},{"y":2024,"m":8,"oil":24.5,"gas":0.84,"water":2189.06},{"y":2024,"m":9,"oil":26.12,"gas":0.93,"water":2824.65},{"y":2024,"m":10,"oil":24.81,"gas":0.96,"water":2667.67},{"y":2024,"m":11,"oil":25.71,"gas":1.29,"water":2811.36},{"y":2025,"m":0,"oil":26.43,"gas":1.42,"water":2748.05},{"y":2025,"m":1,"oil":23.74,"gas":1.12,"water":2199.01},{"y":2025,"m":2,"oil":27.79,"gas":1.2,"water":2327.64},{"y":2025,"m":3,"oil":24.81,"gas":0.81,"water":2226.98},{"y":2025,"m":4,"oil":33.35,"gas":0.27,"water":2663.05},{"y":2025,"m":5,"oil":25.28,"gas":0,"water":1972.04},{"y":2025,"m":6,"oil":24.96,"gas":0,"water":2005.84},{"y":2025,"m":7,"oil":25.16,"gas":0,"water":2073.06},{"y":2025,"m":8,"oil":24.19,"gas":0,"water":2014.76},{"y":2025,"m":9,"oil":25.5,"gas":0,"water":2233.73},{"y":2025,"m":10,"oil":24.73,"gas":0,"water":2147.47},{"y":2025,"m":11,"oil":24.72,"gas":0,"water":2219.76},{"y":2026,"m":0,"oil":26.47,"gas":0,"water":2147.13},{"y":2026,"m":1,"oil":24.02,"gas":0,"water":1993.42},{"y":2026,"m":2,"oil":25.79,"gas":1.36,"water":2159.59},{"y":2026,"m":3,"oil":25.28,"gas":1.32,"water":2185.51}]