[{"y":2019,"m":0,"oil":43.26,"gas":8.9,"water":1820.02},{"y":2019,"m":1,"oil":36.97,"gas":7.28,"water":1370.58},{"y":2019,"m":2,"oil":39.44,"gas":7.8,"water":1469.84},{"y":2019,"m":3,"oil":39.53,"gas":10.81,"water":1420.91},{"y":2019,"m":4,"oil":28.46,"gas":10.91,"water":1116.08},{"y":2019,"m":5,"oil":45.03,"gas":12.08,"water":2208.74},{"y":2019,"m":6,"oil":46.39,"gas":12.82,"water":2129.81},{"y":2019,"m":7,"oil":86.21,"gas":10.54,"water":2052.65},{"y":2019,"m":8,"oil":113.04,"gas":9.92,"water":1513.82},{"y":2019,"m":9,"oil":77.44,"gas":8.3,"water":1045.28},{"y":2019,"m":10,"oil":78.82,"gas":10.83,"water":1293.31},{"y":2019,"m":11,"oil":106.52,"gas":14.9,"water":2121.28},{"y":2020,"m":0,"oil":96.08,"gas":17.15,"water":2089.75},{"y":2020,"m":1,"oil":47.67,"gas":8.61,"water":1833.82},{"y":2020,"m":2,"oil":43.05,"gas":7.19,"water":1573.29},{"y":2020,"m":3,"oil":48.49,"gas":8.49,"water":1512.5},{"y":2020,"m":4,"oil":47.68,"gas":9.02,"water":1733.24},{"y":2020,"m":5,"oil":92.69,"gas":8.96,"water":1956.84},{"y":2020,"m":6,"oil":116.67,"gas":8.36,"water":2043.83},{"y":2020,"m":7,"oil":70.01,"gas":2.5,"water":1063.79},{"y":2020,"m":8,"oil":73.59,"gas":4.06,"water":1053.69},{"y":2020,"m":9,"oil":43.63,"gas":2.31,"water":627.91},{"y":2020,"m":10,"oil":13.42,"gas":0.67,"water":199.08},{"y":2020,"m":11,"oil":66.76,"gas":3.29,"water":1091.17},{"y":2021,"m":0,"oil":71.41,"gas":3.16,"water":1183.29},{"y":2021,"m":1,"oil":70.4,"gas":3.05,"water":1041.89},{"y":2021,"m":2,"oil":68.15,"gas":3.05,"water":1024.89},{"y":2021,"m":3,"oil":56.23,"gas":2.88,"water":935.61},{"y":2021,"m":4,"oil":32.96,"gas":3.75,"water":999},{"y":2021,"m":5,"oil":3.26,"gas":1.57,"water":384.62},{"y":2021,"m":6,"oil":0,"gas":0,"water":0},{"y":2021,"m":7,"oil":0,"gas":0,"water":0},{"y":2021,"m":8,"oil":0,"gas":0,"water":0},{"y":2021,"m":9,"oil":0,"gas":0,"water":0},{"y":2021,"m":10,"oil":0,"gas":0,"water":0},{"y":2021,"m":11,"oil":0,"gas":0,"water":0},{"y":2022,"m":0,"oil":0,"gas":0,"water":0},{"y":2022,"m":1,"oil":0,"gas":0,"water":0},{"y":2022,"m":2,"oil":0,"gas":0,"water":0},{"y":2022,"m":3,"oil":0,"gas":0,"water":0},{"y":2022,"m":4,"oil":0,"gas":0,"water":0},{"y":2022,"m":5,"oil":0,"gas":0,"water":0},{"y":2022,"m":6,"oil":0,"gas":0,"water":0},{"y":2022,"m":7,"oil":0,"gas":0,"water":0},{"y":2022,"m":8,"oil":0,"gas":0,"water":0},{"y":2022,"m":9,"oil":0,"gas":0,"water":0},{"y":2022,"m":10,"oil":0,"gas":0,"water":0},{"y":2022,"m":11,"oil":0,"gas":0,"water":0},{"y":2023,"m":0,"oil":0,"gas":0,"water":0},{"y":2023,"m":1,"oil":0,"gas":0,"water":0},{"y":2023,"m":2,"oil":0,"gas":0,"water":0},{"y":2023,"m":3,"oil":0,"gas":0,"water":0},{"y":2023,"m":4,"oil":0,"gas":0,"water":0},{"y":2023,"m":5,"oil":0,"gas":0,"water":0},{"y":2023,"m":6,"oil":0,"gas":0,"water":0},{"y":2023,"m":7,"oil":0,"gas":0,"water":0},{"y":2023,"m":8,"oil":0,"gas":0,"water":0},{"y":2023,"m":9,"oil":0,"gas":0,"water":0},{"y":2023,"m":10,"oil":0,"gas":0,"water":0},{"y":2023,"m":11,"oil":0,"gas":0,"water":0},{"y":2024,"m":0,"oil":0,"gas":0,"water":0},{"y":2024,"m":1,"oil":0,"gas":0,"water":0},{"y":2024,"m":2,"oil":0,"gas":0,"water":0},{"y":2024,"m":3,"oil":0,"gas":0,"water":0},{"y":2024,"m":4,"oil":0,"gas":0,"water":0},{"y":2024,"m":5,"oil":0,"gas":0,"water":0},{"y":2024,"m":6,"oil":0,"gas":0,"water":0},{"y":2024,"m":7,"oil":49.27,"gas":17.23,"water":844.91},{"y":2024,"m":8,"oil":44.6,"gas":23.77,"water":1318.04},{"y":2024,"m":9,"oil":36.04,"gas":15.83,"water":1275.76},{"y":2024,"m":10,"oil":23.6,"gas":13.14,"water":1096.22},{"y":2024,"m":11,"oil":48.36,"gas":10.55,"water":897.2},{"y":2025,"m":0,"oil":86.53,"gas":11.19,"water":804.51},{"y":2025,"m":1,"oil":66.2,"gas":7.37,"water":637.47},{"y":2025,"m":2,"oil":92.89,"gas":10.55,"water":845.49},{"y":2025,"m":3,"oil":94.5,"gas":9.4,"water":747.61},{"y":2025,"m":4,"oil":150.67,"gas":9.54,"water":708.27},{"y":2025,"m":5,"oil":150.52,"gas":9.72,"water":738.78},{"y":2025,"m":6,"oil":138.04,"gas":9.87,"water":776.8},{"y":2025,"m":7,"oil":142.76,"gas":7.79,"water":714.54},{"y":2025,"m":8,"oil":120.15,"gas":6.77,"water":630.65},{"y":2025,"m":9,"oil":72.29,"gas":6.18,"water":576.94},{"y":2025,"m":10,"oil":35.16,"gas":3.26,"water":282.58},{"y":2025,"m":11,"oil":49.16,"gas":4.82,"water":380.42},{"y":2026,"m":0,"oil":85.2,"gas":7.16,"water":543.55},{"y":2026,"m":1,"oil":94.19,"gas":6.91,"water":744.05},{"y":2026,"m":2,"oil":143.09,"gas":7.13,"water":762.09},{"y":2026,"m":3,"oil":147.92,"gas":7.04,"water":661.92}]