[{"y":2019,"m":0,"oil":84.47,"gas":6.58838,"water":286.58},{"y":2019,"m":1,"oil":81.92,"gas":6.30774,"water":254.08},{"y":2019,"m":2,"oil":84.88,"gas":6.45095,"water":250.62},{"y":2019,"m":3,"oil":81.14,"gas":6.00409,"water":248.86},{"y":2019,"m":4,"oil":86.42,"gas":6.48151,"water":252.75},{"y":2019,"m":5,"oil":72.33,"gas":5.56958,"water":242.67},{"y":2019,"m":6,"oil":62.77,"gas":4.77021,"water":244.73},{"y":2019,"m":7,"oil":89.34,"gas":6.34293,"water":282.66},{"y":2019,"m":8,"oil":76.66,"gas":5.28942,"water":245.84},{"y":2019,"m":9,"oil":82.19,"gas":5.42457,"water":281.81},{"y":2019,"m":10,"oil":76.13,"gas":4.03492,"water":252.27},{"y":2019,"m":11,"oil":72,"gas":3.81608,"water":255},{"y":2020,"m":0,"oil":66.23,"gas":3.5104,"water":225.49},{"y":2020,"m":1,"oil":63.21,"gas":3.91877,"water":273.79},{"y":2020,"m":2,"oil":92.41,"gas":5.72951,"water":279.59},{"y":2020,"m":3,"oil":90.89,"gas":5.63502,"water":267.11},{"y":2020,"m":4,"oil":91.94,"gas":5.70041,"water":276.81},{"y":2020,"m":5,"oil":89.19,"gas":5.52993,"water":268.23},{"y":2020,"m":6,"oil":91.25,"gas":7.07235,"water":274.74},{"y":2020,"m":7,"oil":94.76,"gas":7.34368,"water":538.22},{"y":2020,"m":8,"oil":94.18,"gas":7.29925,"water":481.02},{"y":2020,"m":9,"oil":108.71,"gas":8.42474,"water":774.32},{"y":2020,"m":10,"oil":102.3,"gas":7.92809,"water":683.01},{"y":2020,"m":11,"oil":105.36,"gas":8.16575,"water":681.14},{"y":2021,"m":0,"oil":87.03,"gas":6.74517,"water":378.69},{"y":2021,"m":1,"oil":67.68,"gas":5.24511,"water":273.92},{"y":2021,"m":2,"oil":55.41,"gas":3.95099,"water":223.25},{"y":2021,"m":3,"oil":37.07,"gas":2.64339,"water":440.07},{"y":2021,"m":4,"oil":58.58,"gas":4.7215,"water":659.35},{"y":2021,"m":5,"oil":60.35,"gas":5.05138,"water":741.61},{"y":2021,"m":6,"oil":60.79,"gas":5.08847,"water":455.58},{"y":2021,"m":7,"oil":92.25,"gas":7.72157,"water":598.87},{"y":2021,"m":8,"oil":85.4,"gas":7.14828,"water":732.14},{"y":2021,"m":9,"oil":89.76,"gas":7.51315,"water":670.77},{"y":2021,"m":10,"oil":129.52,"gas":10.84058,"water":602.08},{"y":2021,"m":11,"oil":104.2,"gas":8.72,"water":803.18},{"y":2022,"m":0,"oil":108.88,"gas":9.11,"water":768.35},{"y":2022,"m":1,"oil":110.19,"gas":9.22,"water":692.39},{"y":2022,"m":2,"oil":113.73,"gas":9.52,"water":713.14},{"y":2022,"m":3,"oil":88.85,"gas":7.44,"water":650.88},{"y":2022,"m":4,"oil":85.29,"gas":7.14,"water":655.38},{"y":2022,"m":5,"oil":85.34,"gas":7.14,"water":655.65},{"y":2022,"m":6,"oil":85.45,"gas":7.15,"water":678.15},{"y":2022,"m":7,"oil":95.08,"gas":7.96,"water":670.62},{"y":2022,"m":8,"oil":90.75,"gas":7.6,"water":639.66},{"y":2022,"m":9,"oil":78.53,"gas":6.57,"water":674.1},{"y":2022,"m":10,"oil":80.51,"gas":6.74,"water":591.89},{"y":2022,"m":11,"oil":84.07,"gas":7.04,"water":667.5},{"y":2023,"m":0,"oil":73.53,"gas":6.15,"water":626.68},{"y":2023,"m":1,"oil":68.42,"gas":5.73,"water":572.78},{"y":2023,"m":2,"oil":78.37,"gas":6.56,"water":672.8},{"y":2023,"m":3,"oil":84.85,"gas":7.66,"water":690.89},{"y":2023,"m":4,"oil":55.79,"gas":5.06,"water":818.49},{"y":2023,"m":5,"oil":34.47,"gas":3.27,"water":655.6},{"y":2023,"m":6,"oil":20.03,"gas":1.77,"water":382.56},{"y":2023,"m":7,"oil":0,"gas":0,"water":0},{"y":2023,"m":8,"oil":8.11,"gas":0.74,"water":153.61},{"y":2023,"m":9,"oil":33.71,"gas":3.01,"water":837.25},{"y":2023,"m":10,"oil":40.97,"gas":3.6,"water":850.91},{"y":2023,"m":11,"oil":41.7953,"gas":3.7329,"water":827.7465},{"y":2024,"m":0,"oil":32.9851,"gas":2.8821,"water":885.1663},{"y":2024,"m":1,"oil":5.7734,"gas":0.5412,"water":169.7125},{"y":2024,"m":2,"oil":35.6831,"gas":3.3044,"water":1136.2582},{"y":2024,"m":3,"oil":44.2272,"gas":4.124,"water":967.6205},{"y":2024,"m":4,"oil":41.67844,"gas":6.774523,"water":1602.816},{"y":2024,"m":5,"oil":35.79672,"gas":6.830616,"water":621.5942},{"y":2024,"m":6,"oil":31.99726,"gas":8.163046,"water":951.7209},{"y":2024,"m":7,"oil":29.3668,"gas":8.043632,"water":733.0056},{"y":2024,"m":8,"oil":18.25395,"gas":8.163124,"water":519.352},{"y":2024,"m":9,"oil":13.44221,"gas":1.077043,"water":487.5751},{"y":2024,"m":10,"oil":8.853349,"gas":0.1966403,"water":447.6212},{"y":2024,"m":11,"oil":19.92807,"gas":8.381559,"water":699.3051},{"y":2025,"m":0,"oil":49.2407,"gas":8.714327,"water":723.6004},{"y":2025,"m":1,"oil":62.74608,"gas":7.390053,"water":889.2131},{"y":2025,"m":2,"oil":18.47711,"gas":1.296774,"water":547.9191},{"y":2025,"m":3,"oil":7.431148,"gas":0.683053,"water":339.3887},{"y":2025,"m":4,"oil":7.173,"gas":0.053,"water":168.146},{"y":2025,"m":5,"oil":19.803,"gas":2.126,"water":490.596},{"y":2025,"m":6,"oil":13.567,"gas":1.279,"water":640.514},{"y":2025,"m":7,"oil":41.936,"gas":8.203,"water":1069.931},{"y":2025,"m":8,"oil":53.813,"gas":8.916,"water":944.8},{"y":2025,"m":9,"oil":72.492,"gas":8.482,"water":936.076},{"y":2025,"m":10,"oil":67.922,"gas":9.17,"water":902.6},{"y":2025,"m":11,"oil":72.1,"gas":9.013,"water":908.821},{"y":2026,"m":0,"oil":71.951,"gas":7.026,"water":935.648},{"y":2026,"m":1,"oil":65.42,"gas":6.467,"water":845.389},{"y":2026,"m":2,"oil":66.692,"gas":8.011,"water":960.852},{"y":2026,"m":3,"oil":65.833,"gas":7.233,"water":951.584}]