[{"y":2019,"m":0,"oil":4.07,"gas":370.81,"water":1190.84},{"y":2019,"m":1,"oil":0.67,"gas":1441.72,"water":910.76},{"y":2019,"m":2,"oil":8.56,"gas":991.3,"water":1269.59},{"y":2019,"m":3,"oil":41.91,"gas":741.91,"water":2921.49},{"y":2019,"m":4,"oil":2.54,"gas":37.01,"water":3154.28},{"y":2019,"m":5,"oil":2.54,"gas":7.07,"water":3202.13},{"y":2019,"m":6,"oil":3.11,"gas":7.91,"water":3981.66},{"y":2019,"m":7,"oil":38.02,"gas":8.17,"water":4661.72},{"y":2019,"m":8,"oil":32.5,"gas":8.01,"water":4563.93},{"y":2019,"m":9,"oil":4.01,"gas":7.82,"water":4871.8},{"y":2019,"m":10,"oil":3.36,"gas":6.72,"water":4194.37},{"y":2019,"m":11,"oil":4.12,"gas":6.62,"water":4877.34},{"y":2020,"m":0,"oil":4.04,"gas":6.53,"water":4729.12},{"y":2020,"m":1,"oil":18.5,"gas":5.6,"water":3963.03},{"y":2020,"m":2,"oil":30.61,"gas":6.68,"water":3625.04},{"y":2020,"m":3,"oil":27.44,"gas":6.73,"water":3262.85},{"y":2020,"m":4,"oil":29.93,"gas":6.92,"water":3681.51},{"y":2020,"m":5,"oil":32.8,"gas":6.73,"water":3686.7},{"y":2020,"m":6,"oil":30.65,"gas":9.26,"water":3732.77},{"y":2020,"m":7,"oil":29.39,"gas":10.42,"water":3768.07},{"y":2020,"m":8,"oil":28.82,"gas":7.55,"water":3814.7},{"y":2020,"m":9,"oil":32.27,"gas":8.21,"water":3807.23},{"y":2020,"m":10,"oil":22.97,"gas":6.04,"water":2863.12},{"y":2020,"m":11,"oil":35.26,"gas":9.73,"water":4152.01},{"y":2021,"m":0,"oil":34.02,"gas":13.5,"water":4247.54},{"y":2021,"m":1,"oil":27.01,"gas":6.12,"water":3595.33},{"y":2021,"m":2,"oil":32.87,"gas":6.48,"water":4086.97},{"y":2021,"m":3,"oil":21.87,"gas":3.7,"water":2744.78},{"y":2021,"m":4,"oil":0,"gas":0,"water":0},{"y":2021,"m":5,"oil":17.75,"gas":5.76,"water":2213.13},{"y":2021,"m":6,"oil":24.72,"gas":7.88,"water":3087.01},{"y":2021,"m":7,"oil":26.79,"gas":7.16,"water":3299.3},{"y":2021,"m":8,"oil":27.86,"gas":6.98,"water":3352.48},{"y":2021,"m":9,"oil":21.81,"gas":12.85,"water":3655.08},{"y":2021,"m":10,"oil":14.4,"gas":9.29,"water":3525.9},{"y":2021,"m":11,"oil":27.3,"gas":6.82,"water":3359.65},{"y":2022,"m":0,"oil":28.47,"gas":5.63,"water":3089.62},{"y":2022,"m":1,"oil":30.61,"gas":4.29,"water":3153.87},{"y":2022,"m":2,"oil":39.19,"gas":6.24,"water":4113.94},{"y":2022,"m":3,"oil":32.18,"gas":12.51,"water":3537.1},{"y":2022,"m":4,"oil":33.44,"gas":13.05,"water":3920.41},{"y":2022,"m":5,"oil":33.33,"gas":9.97,"water":3835.35},{"y":2022,"m":6,"oil":34.75,"gas":10.35,"water":4075.21},{"y":2022,"m":7,"oil":30.64,"gas":9.18,"water":3764.02},{"y":2022,"m":8,"oil":32.48,"gas":6.05,"water":3652.1},{"y":2022,"m":9,"oil":33.02,"gas":4.45,"water":3619.76},{"y":2022,"m":10,"oil":28.73,"gas":5.49,"water":3266.84},{"y":2022,"m":11,"oil":24.81,"gas":5.8,"water":2822.47},{"y":2023,"m":0,"oil":29.23,"gas":6.76,"water":3266.36},{"y":2023,"m":1,"oil":27.23,"gas":5.59,"water":2952.62},{"y":2023,"m":2,"oil":31.13,"gas":6.34,"water":3472.34},{"y":2023,"m":3,"oil":37.73,"gas":6.91,"water":4353.32},{"y":2023,"m":4,"oil":37.98,"gas":7.57,"water":4333.3},{"y":2023,"m":5,"oil":39,"gas":10.2,"water":4571.92},{"y":2023,"m":6,"oil":39.83,"gas":12.78,"water":4838.68},{"y":2023,"m":7,"oil":43.05,"gas":10.14,"water":5247.5},{"y":2023,"m":8,"oil":20.81,"gas":9.54,"water":4775.85},{"y":2023,"m":9,"oil":32.45,"gas":8.76,"water":4118.7},{"y":2023,"m":10,"oil":24.42,"gas":10.67,"water":3746.61},{"y":2023,"m":11,"oil":2.07,"gas":5.7,"water":2261.82},{"y":2024,"m":0,"oil":11.93,"gas":8.11,"water":3961.73},{"y":2024,"m":1,"oil":17.55,"gas":8,"water":3545.12},{"y":2024,"m":2,"oil":11.72,"gas":4.84,"water":2425},{"y":2024,"m":3,"oil":11.85,"gas":5.6,"water":2850.4},{"y":2024,"m":4,"oil":11.42,"gas":6.51,"water":3551.31},{"y":2024,"m":5,"oil":14.09,"gas":4.45,"water":3080.69},{"y":2024,"m":6,"oil":14.2,"gas":2.77,"water":2993.37},{"y":2024,"m":7,"oil":22.89,"gas":4.54,"water":4845.33},{"y":2024,"m":8,"oil":15.15,"gas":3.61,"water":4149.37},{"y":2024,"m":9,"oil":16.31,"gas":3.88,"water":3596.79},{"y":2024,"m":10,"oil":19.04,"gas":5.48,"water":3671.67},{"y":2024,"m":11,"oil":17.88,"gas":5.41,"water":4170.66},{"y":2025,"m":0,"oil":20.28,"gas":4,"water":4285.56},{"y":2025,"m":1,"oil":26.94,"gas":8.21,"water":4074},{"y":2025,"m":2,"oil":30.24,"gas":5.82,"water":4446.48},{"y":2025,"m":3,"oil":16.95,"gas":5.76,"water":4178.09},{"y":2025,"m":4,"oil":18.91,"gas":9.5,"water":4670.81},{"y":2025,"m":5,"oil":19.78,"gas":12.05,"water":4419.41},{"y":2025,"m":6,"oil":18.77,"gas":2.06,"water":3948.21},{"y":2025,"m":7,"oil":19.84,"gas":5.28,"water":4450.03},{"y":2025,"m":8,"oil":19.75,"gas":4.81,"water":4330.52},{"y":2025,"m":9,"oil":17.26,"gas":4.54,"water":4616.76},{"y":2025,"m":10,"oil":17.28,"gas":4.89,"water":4586.18},{"y":2025,"m":11,"oil":11.10005,"gas":5.524818,"water":5039.505},{"y":2026,"m":0,"oil":12.16423,"gas":4.987529,"water":5708.017},{"y":2026,"m":1,"oil":10.54604,"gas":3.594644,"water":4937.071},{"y":2026,"m":2,"oil":2.734975,"gas":0.788714,"water":1167.818},{"y":2026,"m":3,"oil":8.677902,"gas":3.134941,"water":4108.759}]