[{"y":2019,"m":0,"oil":7.39,"gas":1.01,"water":139.67},{"y":2019,"m":1,"oil":7.74,"gas":0.95,"water":125.45},{"y":2019,"m":2,"oil":8.82,"gas":1.2,"water":132.08},{"y":2019,"m":3,"oil":13.71,"gas":1.91,"water":137.42},{"y":2019,"m":4,"oil":25.05,"gas":2.82,"water":180.27},{"y":2019,"m":5,"oil":18.12,"gas":1.77,"water":146.38},{"y":2019,"m":6,"oil":17.17,"gas":2.05,"water":143.72},{"y":2019,"m":7,"oil":11.22,"gas":1.68,"water":136.95},{"y":2019,"m":8,"oil":34.62,"gas":5.19,"water":103.59},{"y":2019,"m":9,"oil":52.97,"gas":7.9,"water":85.4},{"y":2019,"m":10,"oil":62.45,"gas":10.36,"water":115.8},{"y":2019,"m":11,"oil":68.15,"gas":9.73,"water":134.87},{"y":2020,"m":0,"oil":71.71,"gas":8.82,"water":167.13},{"y":2020,"m":1,"oil":63.01,"gas":7.06,"water":171.45},{"y":2020,"m":2,"oil":69.83,"gas":6.74,"water":182.17},{"y":2020,"m":3,"oil":68.58,"gas":7.12,"water":183.9},{"y":2020,"m":4,"oil":84.25,"gas":7.35,"water":178.39},{"y":2020,"m":5,"oil":86.08,"gas":8.97,"water":171.65},{"y":2020,"m":6,"oil":64.17,"gas":5.88,"water":196.55},{"y":2020,"m":7,"oil":53.94,"gas":4.8,"water":202.85},{"y":2020,"m":8,"oil":65.1,"gas":7.51,"water":168.93},{"y":2020,"m":9,"oil":68.28,"gas":7.47,"water":179.17},{"y":2020,"m":10,"oil":66.52,"gas":7.19,"water":178.26},{"y":2020,"m":11,"oil":70.03,"gas":7.29,"water":202.97},{"y":2021,"m":0,"oil":58.37,"gas":5.6,"water":413.2},{"y":2021,"m":1,"oil":51.7,"gas":4.54,"water":378.41},{"y":2021,"m":2,"oil":87.73,"gas":8.71,"water":376.71},{"y":2021,"m":3,"oil":93.31,"gas":9.27,"water":347.47},{"y":2021,"m":4,"oil":86.78,"gas":8.9,"water":389.74},{"y":2021,"m":5,"oil":84.21,"gas":8.8,"water":370.04},{"y":2021,"m":6,"oil":13.57,"gas":0.71,"water":59.83},{"y":2021,"m":7,"oil":55.24,"gas":6.07,"water":273.71},{"y":2021,"m":8,"oil":26.81,"gas":4.4,"water":229.32},{"y":2021,"m":9,"oil":25.97,"gas":6.36,"water":226.77},{"y":2021,"m":10,"oil":28.32,"gas":6.36,"water":224.34},{"y":2021,"m":11,"oil":35.78,"gas":7.25,"water":202.3},{"y":2022,"m":0,"oil":42.3,"gas":8.12,"water":223.35},{"y":2022,"m":1,"oil":59.04,"gas":4.39,"water":267.77},{"y":2022,"m":2,"oil":64.08,"gas":4.75,"water":300.07},{"y":2022,"m":3,"oil":65.78,"gas":3.81,"water":417.18},{"y":2022,"m":4,"oil":68.01,"gas":3.8,"water":441.64},{"y":2022,"m":5,"oil":64.81,"gas":3.59,"water":396.32},{"y":2022,"m":6,"oil":91.19,"gas":5.01,"water":415.04},{"y":2022,"m":7,"oil":90.45,"gas":4.25,"water":417.52},{"y":2022,"m":8,"oil":91.41,"gas":3.79,"water":433.67},{"y":2022,"m":9,"oil":163.81,"gas":6.29,"water":425.38},{"y":2022,"m":10,"oil":153.98,"gas":5.02,"water":349.55},{"y":2022,"m":11,"oil":146.96,"gas":4.16,"water":387.96},{"y":2023,"m":0,"oil":144.42,"gas":4.04,"water":380.22},{"y":2023,"m":1,"oil":121.53,"gas":6.47,"water":340.92},{"y":2023,"m":2,"oil":132.23,"gas":5.37,"water":367.67},{"y":2023,"m":3,"oil":131.15,"gas":5.27,"water":369.24},{"y":2023,"m":4,"oil":137.32,"gas":6.44,"water":389.25},{"y":2023,"m":5,"oil":113.37,"gas":3.6,"water":394.36},{"y":2023,"m":6,"oil":112.66,"gas":4.18,"water":390.92},{"y":2023,"m":7,"oil":113.55,"gas":8.27,"water":400.19},{"y":2023,"m":8,"oil":118.59,"gas":7.52,"water":378.31},{"y":2023,"m":9,"oil":152.24,"gas":13.91,"water":351.78},{"y":2023,"m":10,"oil":146.06,"gas":12.75,"water":335.97},{"y":2023,"m":11,"oil":153.5,"gas":14.56,"water":344.78},{"y":2024,"m":0,"oil":138.21,"gas":14.97,"water":417.44},{"y":2024,"m":1,"oil":94.03,"gas":9.76,"water":523.9},{"y":2024,"m":2,"oil":101.57,"gas":11.7,"water":553.45},{"y":2024,"m":3,"oil":95.63,"gas":10.77,"water":551.44},{"y":2024,"m":4,"oil":93.39,"gas":8.46,"water":342.78},{"y":2024,"m":5,"oil":54.24,"gas":5.82,"water":178.09},{"y":2024,"m":6,"oil":77.14,"gas":3.9,"water":224.35},{"y":2024,"m":7,"oil":90.76,"gas":4.91,"water":287.45},{"y":2024,"m":8,"oil":91,"gas":5.48,"water":279},{"y":2024,"m":9,"oil":100.1,"gas":6.29,"water":353.16},{"y":2024,"m":10,"oil":60.81,"gas":5.01,"water":372.12},{"y":2024,"m":11,"oil":60.09,"gas":4.86,"water":395.13},{"y":2025,"m":0,"oil":61.19,"gas":5.25,"water":386.31},{"y":2025,"m":1,"oil":50.59,"gas":3.83,"water":337.15},{"y":2025,"m":2,"oil":56.28,"gas":3.69,"water":397.08},{"y":2025,"m":3,"oil":57.37,"gas":3.62,"water":377.66},{"y":2025,"m":4,"oil":90.65,"gas":5.67,"water":349.15},{"y":2025,"m":5,"oil":88.56,"gas":6.29,"water":336.97},{"y":2025,"m":6,"oil":88.33,"gas":4.57,"water":348.75},{"y":2025,"m":7,"oil":97.07,"gas":4.74,"water":347.07},{"y":2025,"m":8,"oil":115.2,"gas":4.4,"water":332.4},{"y":2025,"m":9,"oil":120.44,"gas":2.63,"water":345.72},{"y":2025,"m":10,"oil":99.69,"gas":2.58,"water":281.81},{"y":2025,"m":11,"oil":114.43,"gas":2.92,"water":325.82},{"y":2026,"m":0,"oil":117.79,"gas":2.83,"water":331.01},{"y":2026,"m":1,"oil":120.09,"gas":4.12,"water":267.26},{"y":2026,"m":2,"oil":123.87,"gas":5.04,"water":304.17},{"y":2026,"m":3,"oil":80.19,"gas":4.38,"water":339.63}]