[{"y":2019,"m":0,"oil":119.91,"gas":0,"water":15.61},{"y":2019,"m":1,"oil":134.73,"gas":0,"water":12.22},{"y":2019,"m":2,"oil":137.44,"gas":0,"water":13.65},{"y":2019,"m":3,"oil":117.59,"gas":0,"water":19.05},{"y":2019,"m":4,"oil":90.76,"gas":0,"water":19.5},{"y":2019,"m":5,"oil":88.94,"gas":0,"water":14.15},{"y":2019,"m":6,"oil":99.76,"gas":0,"water":10.44},{"y":2019,"m":7,"oil":104.29,"gas":0,"water":12.84},{"y":2019,"m":8,"oil":89.53,"gas":0,"water":19.43},{"y":2019,"m":9,"oil":79.97,"gas":0,"water":16.95},{"y":2019,"m":10,"oil":0,"gas":0,"water":0},{"y":2019,"m":11,"oil":77.92,"gas":0,"water":19.65},{"y":2020,"m":0,"oil":108.49,"gas":0,"water":28.92},{"y":2020,"m":1,"oil":112.68,"gas":0,"water":28.35},{"y":2020,"m":2,"oil":118.98,"gas":0,"water":34},{"y":2020,"m":3,"oil":94.97,"gas":0,"water":30.21},{"y":2020,"m":4,"oil":104.86,"gas":0,"water":39.12},{"y":2020,"m":5,"oil":110.29,"gas":0,"water":35.29},{"y":2020,"m":6,"oil":109.18,"gas":0,"water":32.59},{"y":2020,"m":7,"oil":113.73,"gas":0,"water":35.88},{"y":2020,"m":8,"oil":101.22,"gas":0,"water":36.13},{"y":2020,"m":9,"oil":106.29,"gas":0,"water":40.56},{"y":2020,"m":10,"oil":112.18,"gas":0,"water":37.07},{"y":2020,"m":11,"oil":90.82,"gas":0,"water":34.48},{"y":2021,"m":0,"oil":93.35,"gas":0,"water":30.81},{"y":2021,"m":1,"oil":82,"gas":0,"water":24.18},{"y":2021,"m":2,"oil":100.25,"gas":0,"water":16.31},{"y":2021,"m":3,"oil":85.63,"gas":0,"water":14.22},{"y":2021,"m":4,"oil":79.97,"gas":0,"water":21.17},{"y":2021,"m":5,"oil":70.33,"gas":0,"water":29.84},{"y":2021,"m":6,"oil":70.12,"gas":0,"water":27.66},{"y":2021,"m":7,"oil":87.2,"gas":0,"water":32.2},{"y":2021,"m":8,"oil":104.6,"gas":0,"water":34.69},{"y":2021,"m":9,"oil":96.27,"gas":0,"water":29.63},{"y":2021,"m":10,"oil":84.01,"gas":0,"water":23.29},{"y":2021,"m":11,"oil":75.68,"gas":0,"water":20.58},{"y":2022,"m":0,"oil":89.56,"gas":0,"water":26.08},{"y":2022,"m":1,"oil":88.93,"gas":0,"water":27.6},{"y":2022,"m":2,"oil":91.63,"gas":0,"water":26.36},{"y":2022,"m":3,"oil":88.58,"gas":0,"water":20.6},{"y":2022,"m":4,"oil":84.47,"gas":0,"water":21.73},{"y":2022,"m":5,"oil":69.75,"gas":0,"water":21.66},{"y":2022,"m":6,"oil":54.42,"gas":0,"water":22.04},{"y":2022,"m":7,"oil":34.95,"gas":0,"water":13.25},{"y":2022,"m":8,"oil":42.01,"gas":0,"water":18.94},{"y":2022,"m":9,"oil":44.23,"gas":0,"water":19.49},{"y":2022,"m":10,"oil":39.89,"gas":0,"water":19.57},{"y":2022,"m":11,"oil":39.56,"gas":0,"water":17.35},{"y":2023,"m":0,"oil":35.75,"gas":0,"water":20.56},{"y":2023,"m":1,"oil":0,"gas":0,"water":0},{"y":2023,"m":2,"oil":1.04,"gas":0,"water":0.6},{"y":2023,"m":3,"oil":37.26,"gas":0,"water":25.09},{"y":2023,"m":4,"oil":25.3,"gas":0,"water":25.66},{"y":2023,"m":5,"oil":13.55,"gas":0,"water":29.58},{"y":2023,"m":6,"oil":2.08,"gas":0,"water":4.6},{"y":2023,"m":7,"oil":9.5,"gas":0,"water":20.98},{"y":2023,"m":8,"oil":10.92,"gas":0,"water":24.72},{"y":2023,"m":9,"oil":12.85,"gas":0,"water":30.23},{"y":2023,"m":10,"oil":15.08,"gas":0,"water":38.08},{"y":2023,"m":11,"oil":15.95,"gas":0,"water":39.5},{"y":2024,"m":0,"oil":16,"gas":0,"water":37.74},{"y":2024,"m":1,"oil":14.87,"gas":0,"water":38.07},{"y":2024,"m":2,"oil":13.4,"gas":0,"water":31.16},{"y":2024,"m":3,"oil":19.28,"gas":0,"water":28.07},{"y":2024,"m":4,"oil":12.03,"gas":0,"water":13.84},{"y":2024,"m":5,"oil":11.71,"gas":0,"water":12.11},{"y":2024,"m":6,"oil":12.32,"gas":0,"water":12.13},{"y":2024,"m":7,"oil":3.27,"gas":0,"water":3.41},{"y":2024,"m":8,"oil":0,"gas":0,"water":0},{"y":2024,"m":9,"oil":0,"gas":0,"water":0},{"y":2024,"m":10,"oil":11.4,"gas":0,"water":13.75},{"y":2024,"m":11,"oil":2.4,"gas":0,"water":2.88},{"y":2025,"m":0,"oil":12.25,"gas":0,"water":14.66},{"y":2025,"m":1,"oil":13.53,"gas":0,"water":16.51},{"y":2025,"m":2,"oil":15.2,"gas":0,"water":17.18},{"y":2025,"m":3,"oil":15.52,"gas":0,"water":16.98},{"y":2025,"m":4,"oil":10.35,"gas":0,"water":12.06},{"y":2025,"m":5,"oil":0,"gas":0,"water":0},{"y":2025,"m":6,"oil":0,"gas":0,"water":0},{"y":2025,"m":7,"oil":0,"gas":0,"water":0},{"y":2025,"m":8,"oil":0,"gas":0,"water":0},{"y":2025,"m":9,"oil":0,"gas":0,"water":0},{"y":2025,"m":10,"oil":0,"gas":0,"water":0},{"y":2025,"m":11,"oil":0,"gas":0,"water":0},{"y":2026,"m":0,"oil":0,"gas":0,"water":0},{"y":2026,"m":1,"oil":0,"gas":0,"water":0},{"y":2026,"m":2,"oil":0,"gas":0,"water":0},{"y":2026,"m":3,"oil":0,"gas":0,"water":0}]