[{"y":2019,"m":0,"oil":27.74,"gas":0,"water":627.65},{"y":2019,"m":1,"oil":22.65,"gas":0,"water":511.54},{"y":2019,"m":2,"oil":25.09,"gas":0,"water":563.54},{"y":2019,"m":3,"oil":21.63,"gas":0,"water":550.6},{"y":2019,"m":4,"oil":22.76,"gas":0,"water":515.8},{"y":2019,"m":5,"oil":18.14,"gas":0,"water":491.47},{"y":2019,"m":6,"oil":4.12,"gas":0,"water":149.93},{"y":2019,"m":7,"oil":0,"gas":0,"water":0},{"y":2019,"m":8,"oil":0,"gas":0,"water":0},{"y":2019,"m":9,"oil":0,"gas":0,"water":0},{"y":2019,"m":10,"oil":0,"gas":0,"water":0},{"y":2019,"m":11,"oil":0,"gas":0,"water":0},{"y":2020,"m":0,"oil":0,"gas":0,"water":0},{"y":2020,"m":1,"oil":0,"gas":0,"water":0},{"y":2020,"m":2,"oil":1.152697,"gas":0,"water":300.1472},{"y":2020,"m":3,"oil":7.338702,"gas":0,"water":1504.352},{"y":2020,"m":4,"oil":40.04189,"gas":0,"water":1421.299},{"y":2020,"m":5,"oil":36.28031,"gas":0,"water":1277.507},{"y":2020,"m":6,"oil":25.67137,"gas":0,"water":1223.257},{"y":2020,"m":7,"oil":17.39817,"gas":0,"water":733.1725},{"y":2020,"m":8,"oil":22.48163,"gas":0,"water":900.6704},{"y":2020,"m":9,"oil":0,"gas":0,"water":0},{"y":2020,"m":10,"oil":0,"gas":0,"water":23.74526},{"y":2020,"m":11,"oil":9.688851,"gas":0,"water":1133.189},{"y":2021,"m":0,"oil":19.03859,"gas":0,"water":974.2522},{"y":2021,"m":1,"oil":17.65377,"gas":0,"water":998.2409},{"y":2021,"m":2,"oil":18.81945,"gas":0,"water":1086.834},{"y":2021,"m":3,"oil":18.70813,"gas":0,"water":1000.636},{"y":2021,"m":4,"oil":14.86276,"gas":0,"water":907.8799},{"y":2021,"m":5,"oil":0,"gas":0,"water":0},{"y":2021,"m":6,"oil":0.707415,"gas":0,"water":127.5367},{"y":2021,"m":7,"oil":11.72749,"gas":0,"water":1199.848},{"y":2021,"m":8,"oil":15.415,"gas":0,"water":1197.362},{"y":2021,"m":9,"oil":21.64371,"gas":0,"water":1281.053},{"y":2021,"m":10,"oil":22.12384,"gas":0,"water":1134.169},{"y":2021,"m":11,"oil":22.44801,"gas":0,"water":1106.83},{"y":2022,"m":0,"oil":24.34473,"gas":0,"water":1198.046},{"y":2022,"m":1,"oil":20.88782,"gas":0,"water":947.1364},{"y":2022,"m":2,"oil":22.29199,"gas":0,"water":1000.082},{"y":2022,"m":3,"oil":22.37035,"gas":0,"water":1122.14},{"y":2022,"m":4,"oil":22.2125,"gas":0,"water":1240.64},{"y":2022,"m":5,"oil":21.78787,"gas":0,"water":1151.213},{"y":2022,"m":6,"oil":24.57957,"gas":0,"water":1155.727},{"y":2022,"m":7,"oil":24.56585,"gas":0,"water":1181.811},{"y":2022,"m":8,"oil":24.52674,"gas":0,"water":1131.202},{"y":2022,"m":9,"oil":30.16334,"gas":0,"water":1064.796},{"y":2022,"m":10,"oil":27.24771,"gas":0,"water":986.1607},{"y":2022,"m":11,"oil":26.79229,"gas":0,"water":1029.509},{"y":2023,"m":0,"oil":26.10167,"gas":0,"water":1028.769},{"y":2023,"m":1,"oil":25.9177,"gas":0,"water":924.4931},{"y":2023,"m":2,"oil":25.10229,"gas":0,"water":1006.699},{"y":2023,"m":3,"oil":27.7055,"gas":0,"water":1040.271},{"y":2023,"m":4,"oil":21.61918,"gas":0,"water":982.1898},{"y":2023,"m":5,"oil":24.0446,"gas":0,"water":931.0083},{"y":2023,"m":6,"oil":30.09383,"gas":0,"water":766.9229},{"y":2023,"m":7,"oil":30.31044,"gas":0,"water":765.5856},{"y":2023,"m":8,"oil":30.83319,"gas":0,"water":785.2748},{"y":2023,"m":9,"oil":31.11976,"gas":0,"water":876.9312},{"y":2023,"m":10,"oil":30.41235,"gas":0,"water":915.1937},{"y":2023,"m":11,"oil":34.68138,"gas":0,"water":934.8786},{"y":2024,"m":0,"oil":33.66247,"gas":0,"water":935.916},{"y":2024,"m":1,"oil":33.23327,"gas":0,"water":915.8959},{"y":2024,"m":2,"oil":33.35546,"gas":0,"water":886.6281},{"y":2024,"m":3,"oil":26.05609,"gas":0,"water":829.3057},{"y":2024,"m":4,"oil":25.88119,"gas":0,"water":809.2836},{"y":2024,"m":5,"oil":26.96204,"gas":0,"water":720.8154},{"y":2024,"m":6,"oil":33.03038,"gas":0,"water":586.5773},{"y":2024,"m":7,"oil":34.52481,"gas":0,"water":565.0729},{"y":2024,"m":8,"oil":36.26427,"gas":0,"water":576.4596},{"y":2024,"m":9,"oil":39.41546,"gas":0,"water":603.1311},{"y":2024,"m":10,"oil":37.80858,"gas":0,"water":623.916},{"y":2024,"m":11,"oil":36.37959,"gas":0,"water":632.0087},{"y":2025,"m":0,"oil":37.59601,"gas":0,"water":675.6053},{"y":2025,"m":1,"oil":33.74723,"gas":0,"water":626.3203},{"y":2025,"m":2,"oil":37.11668,"gas":0,"water":847.5935},{"y":2025,"m":3,"oil":34.85512,"gas":0,"water":820.039},{"y":2025,"m":4,"oil":33.18412,"gas":0,"water":696.0775},{"y":2025,"m":5,"oil":32.51662,"gas":0,"water":629.8127},{"y":2025,"m":6,"oil":35.15097,"gas":0,"water":633.9266},{"y":2025,"m":7,"oil":35.98354,"gas":0,"water":611.3133},{"y":2025,"m":8,"oil":31.24967,"gas":0,"water":519.3213},{"y":2025,"m":9,"oil":0,"gas":0,"water":0},{"y":2025,"m":10,"oil":27.9655,"gas":0,"water":961.4409},{"y":2025,"m":11,"oil":36.1849,"gas":0,"water":1204.305},{"y":2026,"m":0,"oil":33.46226,"gas":0,"water":1175.627},{"y":2026,"m":1,"oil":3.222956,"gas":0,"water":165.3247},{"y":2026,"m":2,"oil":27.3705,"gas":0,"water":1132.865},{"y":2026,"m":3,"oil":19.10812,"gas":0,"water":692.7019}]