[{"y":2022,"m":1,"oil":75.17,"gas":3882.6,"water":4194.1},{"y":2022,"m":2,"oil":93.82,"gas":4083.03,"water":1881.28},{"y":2022,"m":3,"oil":67.26,"gas":3108.74,"water":1325.08},{"y":2022,"m":4,"oil":53.7,"gas":2682.16,"water":857.84},{"y":2022,"m":5,"oil":43.06,"gas":2222.79,"water":809.49},{"y":2022,"m":6,"oil":42.29,"gas":2143.75,"water":745.47},{"y":2022,"m":7,"oil":40.85,"gas":2080.87,"water":840.79},{"y":2022,"m":8,"oil":39.31,"gas":1931.99,"water":806.12},{"y":2022,"m":9,"oil":38.37,"gas":1838.21,"water":819.17},{"y":2022,"m":10,"oil":40.3,"gas":1752.16,"water":765.49},{"y":2022,"m":11,"oil":37.47,"gas":1678.96,"water":545.14},{"y":2023,"m":0,"oil":32.2,"gas":1548.82,"water":432.56},{"y":2023,"m":1,"oil":28.34,"gas":1437.49,"water":286.61},{"y":2023,"m":2,"oil":31.32,"gas":1499.81,"water":484.27},{"y":2023,"m":3,"oil":25.8,"gas":1411.85,"water":184.16},{"y":2023,"m":4,"oil":19.07,"gas":1092.45,"water":84.06},{"y":2023,"m":5,"oil":21.68,"gas":1210.54,"water":103.5},{"y":2023,"m":6,"oil":23.1,"gas":1264.57,"water":152.56},{"y":2023,"m":7,"oil":24.55,"gas":1161.42,"water":98.07},{"y":2023,"m":8,"oil":25.16,"gas":1160.6,"water":115.32},{"y":2023,"m":9,"oil":25.07,"gas":1173.41,"water":79.31},{"y":2023,"m":10,"oil":20.9,"gas":1026.31,"water":104.96},{"y":2023,"m":11,"oil":16.52,"gas":739.35,"water":66.96},{"y":2024,"m":0,"oil":33.1,"gas":1383.86,"water":423.85},{"y":2024,"m":1,"oil":24.66,"gas":1034.36,"water":317.7},{"y":2024,"m":2,"oil":18.85,"gas":991.61,"water":218.46},{"y":2024,"m":3,"oil":25.2,"gas":1224.83,"water":413.37},{"y":2024,"m":4,"oil":21.31,"gas":1188.62,"water":314.03},{"y":2024,"m":5,"oil":23.26,"gas":1154.83,"water":309.4},{"y":2024,"m":6,"oil":20.73,"gas":976.59,"water":320.66},{"y":2024,"m":7,"oil":14.25,"gas":810.73,"water":119.48},{"y":2024,"m":8,"oil":13.2,"gas":708.06,"water":123.12},{"y":2024,"m":9,"oil":17.95,"gas":899.59,"water":202.94},{"y":2024,"m":10,"oil":29.6,"gas":1431.92,"water":298.19},{"y":2024,"m":11,"oil":18.71,"gas":791.44,"water":269.08},{"y":2025,"m":0,"oil":17.71,"gas":780.51,"water":239.86},{"y":2025,"m":1,"oil":23.28,"gas":671.5,"water":114.48},{"y":2025,"m":2,"oil":26.84,"gas":699.77,"water":83.59},{"y":2025,"m":3,"oil":26.05,"gas":572.03,"water":116.97},{"y":2025,"m":4,"oil":23.12,"gas":532.45,"water":105.48},{"y":2025,"m":5,"oil":110.68,"gas":695.58,"water":252.73},{"y":2025,"m":6,"oil":11.13,"gas":587.31,"water":94.9},{"y":2025,"m":7,"oil":33.67,"gas":387.39,"water":94.38},{"y":2025,"m":8,"oil":83.5,"gas":870.58,"water":113.27},{"y":2025,"m":9,"oil":46.51,"gas":443.61,"water":52.4},{"y":2025,"m":10,"oil":33.21,"gas":787.86,"water":56.42},{"y":2025,"m":11,"oil":31.69,"gas":477.75,"water":53.14},{"y":2026,"m":0,"oil":15.52,"gas":592.74,"water":75.71},{"y":2026,"m":1,"oil":22.32,"gas":571.56,"water":92.51},{"y":2026,"m":2,"oil":25.68,"gas":523.73,"water":114.35},{"y":2026,"m":3,"oil":23.93,"gas":492.33,"water":102.59}]