[{"y":2019,"m":0,"oil":22.29,"gas":0,"water":104.35},{"y":2019,"m":1,"oil":60.23,"gas":0,"water":281.25},{"y":2019,"m":2,"oil":67.42,"gas":0,"water":309.84},{"y":2019,"m":3,"oil":70.37,"gas":0,"water":294.9},{"y":2019,"m":4,"oil":72.85,"gas":0,"water":301.3},{"y":2019,"m":5,"oil":70.43,"gas":0,"water":289.77},{"y":2019,"m":6,"oil":72.61,"gas":0,"water":297.96},{"y":2019,"m":7,"oil":78.39,"gas":0,"water":305.9},{"y":2019,"m":8,"oil":75.761,"gas":0,"water":303.674},{"y":2019,"m":9,"oil":55.236,"gas":0,"water":255.277},{"y":2019,"m":10,"oil":4.126,"gas":0,"water":47.066},{"y":2019,"m":11,"oil":39.335,"gas":0,"water":354.744},{"y":2020,"m":0,"oil":49.344,"gas":0,"water":293.497},{"y":2020,"m":1,"oil":53.483,"gas":0,"water":249.861},{"y":2020,"m":2,"oil":44.164,"gas":0,"water":213.743},{"y":2020,"m":3,"oil":0,"gas":0,"water":0},{"y":2020,"m":4,"oil":0,"gas":0,"water":0},{"y":2020,"m":5,"oil":0,"gas":0,"water":0},{"y":2020,"m":6,"oil":0,"gas":0,"water":0},{"y":2020,"m":7,"oil":0,"gas":0,"water":0},{"y":2020,"m":8,"oil":2.065,"gas":0,"water":9.901},{"y":2020,"m":9,"oil":0,"gas":0,"water":0},{"y":2020,"m":10,"oil":0,"gas":0,"water":0},{"y":2020,"m":11,"oil":0,"gas":0,"water":0},{"y":2021,"m":0,"oil":0,"gas":0,"water":0},{"y":2021,"m":1,"oil":2.161,"gas":0,"water":9.949},{"y":2021,"m":2,"oil":0,"gas":0,"water":0},{"y":2021,"m":3,"oil":0,"gas":0,"water":0},{"y":2021,"m":4,"oil":17.558,"gas":0,"water":80.091},{"y":2021,"m":5,"oil":66.868,"gas":0,"water":313.075},{"y":2021,"m":6,"oil":69.249,"gas":0,"water":326.648},{"y":2021,"m":7,"oil":60.582,"gas":0,"water":346.792},{"y":2021,"m":8,"oil":57.882,"gas":0,"water":323.936},{"y":2021,"m":9,"oil":58.355,"gas":0,"water":344.298},{"y":2021,"m":10,"oil":42.768,"gas":0,"water":244.263},{"y":2021,"m":11,"oil":74.266,"gas":0,"water":406.076},{"y":2022,"m":0,"oil":75.455,"gas":0,"water":400.387},{"y":2022,"m":1,"oil":66.891,"gas":0,"water":364.349},{"y":2022,"m":2,"oil":87.933,"gas":0,"water":613.91},{"y":2022,"m":3,"oil":105.815,"gas":0,"water":620.473},{"y":2022,"m":4,"oil":111.97,"gas":0,"water":689.936},{"y":2022,"m":5,"oil":110.725,"gas":0,"water":723.967},{"y":2022,"m":6,"oil":109.316,"gas":0,"water":747.821},{"y":2022,"m":7,"oil":44.90864,"gas":0,"water":329.595},{"y":2022,"m":8,"oil":35.38111,"gas":0,"water":583.2922},{"y":2022,"m":9,"oil":46.16681,"gas":0,"water":686.715},{"y":2022,"m":10,"oil":45.22019,"gas":0,"water":670.827},{"y":2022,"m":11,"oil":61.3575,"gas":0,"water":606.3375},{"y":2023,"m":0,"oil":53.57976,"gas":0,"water":539.8375},{"y":2023,"m":1,"oil":47.40587,"gas":0,"water":496.2604},{"y":2023,"m":2,"oil":52.83605,"gas":0,"water":545.668},{"y":2023,"m":3,"oil":52.8061,"gas":0,"water":507.2975},{"y":2023,"m":4,"oil":57.52958,"gas":0,"water":552.668},{"y":2023,"m":5,"oil":55.69472,"gas":0,"water":534.84},{"y":2023,"m":6,"oil":59.50511,"gas":0,"water":550.4395},{"y":2023,"m":7,"oil":65.35309,"gas":0,"water":503.498},{"y":2023,"m":8,"oil":58.64982,"gas":0,"water":467.79},{"y":2023,"m":9,"oil":32.27125,"gas":0,"water":300.4419},{"y":2023,"m":10,"oil":56.88119,"gas":0,"water":449.8124},{"y":2023,"m":11,"oil":54.94269,"gas":0,"water":479.4487},{"y":2024,"m":0,"oil":47.69421,"gas":0,"water":466.277},{"y":2024,"m":1,"oil":46.96023,"gas":0,"water":458.5432},{"y":2024,"m":2,"oil":54.80299,"gas":0,"water":508.8195},{"y":2024,"m":3,"oil":47.35691,"gas":0,"water":546.9345},{"y":2024,"m":4,"oil":39.8615,"gas":0,"water":482.787},{"y":2024,"m":5,"oil":34.90173,"gas":0,"water":516.4016},{"y":2024,"m":6,"oil":9.868989,"gas":0,"water":161.3452},{"y":2024,"m":7,"oil":31.23726,"gas":0,"water":466.9234},{"y":2024,"m":8,"oil":41.37382,"gas":0,"water":577.7464},{"y":2024,"m":9,"oil":35.38619,"gas":0,"water":575.5038},{"y":2024,"m":10,"oil":34.88018,"gas":0,"water":559.74},{"y":2024,"m":11,"oil":41.19722,"gas":0,"water":566.6236},{"y":2025,"m":0,"oil":46.23169,"gas":0,"water":579.2198},{"y":2025,"m":1,"oil":33.68908,"gas":0,"water":570.7787},{"y":2025,"m":2,"oil":24.47838,"gas":0,"water":465.2981},{"y":2025,"m":3,"oil":26.09136,"gas":0,"water":377.2227},{"y":2025,"m":4,"oil":0,"gas":0,"water":0},{"y":2025,"m":5,"oil":0,"gas":0,"water":0},{"y":2025,"m":6,"oil":0,"gas":0,"water":0},{"y":2025,"m":7,"oil":0,"gas":0,"water":0},{"y":2025,"m":8,"oil":0,"gas":0,"water":0},{"y":2025,"m":9,"oil":0,"gas":0,"water":0},{"y":2025,"m":10,"oil":0,"gas":0,"water":0},{"y":2025,"m":11,"oil":0,"gas":0,"water":0},{"y":2026,"m":0,"oil":0,"gas":0,"water":0},{"y":2026,"m":1,"oil":0,"gas":0,"water":0},{"y":2026,"m":2,"oil":0,"gas":0,"water":0},{"y":2026,"m":3,"oil":0,"gas":0,"water":0}]