[{"y":2019,"m":0,"oil":72.56135,"gas":0,"water":638.0013},{"y":2019,"m":1,"oil":73.74064,"gas":0,"water":730.0274},{"y":2019,"m":2,"oil":69.45462,"gas":0,"water":849.9716},{"y":2019,"m":3,"oil":57.59197,"gas":0,"water":818.4478},{"y":2019,"m":4,"oil":36.36328,"gas":0,"water":518.9041},{"y":2019,"m":5,"oil":61.941,"gas":0,"water":863.3842},{"y":2019,"m":6,"oil":68.8287,"gas":0,"water":877.4461},{"y":2019,"m":7,"oil":53.7454,"gas":0,"water":1087.933},{"y":2019,"m":8,"oil":48.41846,"gas":0,"water":1109.904},{"y":2019,"m":9,"oil":43.09942,"gas":0,"water":1093.873},{"y":2019,"m":10,"oil":41.81541,"gas":0,"water":1078.056},{"y":2019,"m":11,"oil":52.26353,"gas":0,"water":1139.524},{"y":2020,"m":0,"oil":56.73105,"gas":0,"water":1168.951},{"y":2020,"m":1,"oil":43.57371,"gas":0,"water":1163.061},{"y":2020,"m":2,"oil":32.13274,"gas":0,"water":1347.091},{"y":2020,"m":3,"oil":41.22336,"gas":0,"water":1289.403},{"y":2020,"m":4,"oil":41.46671,"gas":0,"water":1379.337},{"y":2020,"m":5,"oil":31.87996,"gas":0,"water":1376.872},{"y":2020,"m":6,"oil":59.72394,"gas":0,"water":1255.704},{"y":2020,"m":7,"oil":58.0355,"gas":0,"water":1320.929},{"y":2020,"m":8,"oil":34.90642,"gas":0,"water":1260.862},{"y":2020,"m":9,"oil":39.16667,"gas":0,"water":1230.278},{"y":2020,"m":10,"oil":45.39958,"gas":0,"water":1411.901},{"y":2020,"m":11,"oil":37.8465,"gas":0,"water":1439.248},{"y":2021,"m":0,"oil":53.7893,"gas":0,"water":1465.957},{"y":2021,"m":1,"oil":44.11569,"gas":0,"water":1328.53},{"y":2021,"m":2,"oil":48.96862,"gas":0,"water":1483.89},{"y":2021,"m":3,"oil":36.39735,"gas":0,"water":1370.773},{"y":2021,"m":4,"oil":67.42382,"gas":0,"water":1124.589},{"y":2021,"m":5,"oil":57.96617,"gas":0,"water":1112.2},{"y":2021,"m":6,"oil":49.41317,"gas":0,"water":1079.515},{"y":2021,"m":7,"oil":43.26217,"gas":0,"water":1159.627},{"y":2021,"m":8,"oil":45.44644,"gas":0,"water":1101.409},{"y":2021,"m":9,"oil":44.34587,"gas":0,"water":1189.479},{"y":2021,"m":10,"oil":40.10696,"gas":0,"water":1112.27},{"y":2021,"m":11,"oil":34.97579,"gas":0,"water":1153.116},{"y":2022,"m":0,"oil":35.34431,"gas":0,"water":1237.232},{"y":2022,"m":1,"oil":43.84806,"gas":0,"water":990.5939},{"y":2022,"m":2,"oil":41.928,"gas":0,"water":1110.632},{"y":2022,"m":3,"oil":40.62217,"gas":0,"water":1079.369},{"y":2022,"m":4,"oil":39.7859,"gas":0,"water":1241.45},{"y":2022,"m":5,"oil":39.35606,"gas":0,"water":1145.947},{"y":2022,"m":6,"oil":43.72045,"gas":0,"water":1143.311},{"y":2022,"m":7,"oil":49.85625,"gas":0,"water":1078.078},{"y":2022,"m":8,"oil":74.55346,"gas":0,"water":1143.949},{"y":2022,"m":9,"oil":66.1997,"gas":0,"water":1186.205},{"y":2022,"m":10,"oil":62.22394,"gas":0,"water":1147.192},{"y":2022,"m":11,"oil":70.80586,"gas":0,"water":1127.154},{"y":2023,"m":0,"oil":76.73515,"gas":0,"water":1130.619},{"y":2023,"m":1,"oil":70.28821,"gas":0,"water":1020.471},{"y":2023,"m":2,"oil":81.71925,"gas":0,"water":1106.543},{"y":2023,"m":3,"oil":75.05488,"gas":0,"water":1066.791},{"y":2023,"m":4,"oil":62.58204,"gas":0,"water":1021.49},{"y":2023,"m":5,"oil":70.78495,"gas":0,"water":961.3045},{"y":2023,"m":6,"oil":66.11535,"gas":0,"water":998.0865},{"y":2023,"m":7,"oil":70.51493,"gas":0,"water":1098.826},{"y":2023,"m":8,"oil":39.12215,"gas":0,"water":1024.761},{"y":2023,"m":9,"oil":42.97236,"gas":0,"water":1006.119},{"y":2023,"m":10,"oil":35.2634,"gas":0,"water":1216.131},{"y":2023,"m":11,"oil":31.39489,"gas":0,"water":1199.359},{"y":2024,"m":0,"oil":35.29986,"gas":0,"water":1152.39},{"y":2024,"m":1,"oil":39.4447,"gas":0,"water":1084.047},{"y":2024,"m":2,"oil":48.242,"gas":0,"water":1120.425},{"y":2024,"m":3,"oil":49.35749,"gas":0,"water":1019.324},{"y":2024,"m":4,"oil":36.42152,"gas":0,"water":1006.483},{"y":2024,"m":5,"oil":28.56836,"gas":0,"water":1033.489},{"y":2024,"m":6,"oil":29.23252,"gas":0,"water":950.3291},{"y":2024,"m":7,"oil":33.79041,"gas":0,"water":901.672},{"y":2024,"m":8,"oil":32.5412,"gas":0,"water":1021.395},{"y":2024,"m":9,"oil":36.00927,"gas":0,"water":1133.114},{"y":2024,"m":10,"oil":43.8342,"gas":0,"water":1129.204},{"y":2024,"m":11,"oil":42.80293,"gas":0,"water":1101.147},{"y":2025,"m":0,"oil":36.08113,"gas":0,"water":1040.999},{"y":2025,"m":1,"oil":31.91423,"gas":0,"water":348.6541},{"y":2025,"m":2,"oil":33.29277,"gas":0,"water":362.5821},{"y":2025,"m":3,"oil":29.05694,"gas":0,"water":321.7516},{"y":2025,"m":4,"oil":43.32821,"gas":0,"water":420.0972},{"y":2025,"m":5,"oil":44.83782,"gas":0,"water":376.1072},{"y":2025,"m":6,"oil":45.54792,"gas":0,"water":335.654},{"y":2025,"m":7,"oil":45.32458,"gas":0,"water":335.2154},{"y":2025,"m":8,"oil":31.28427,"gas":0,"water":298.193},{"y":2025,"m":9,"oil":16.25682,"gas":0,"water":220.4223},{"y":2025,"m":10,"oil":10.78132,"gas":0,"water":178.6922},{"y":2025,"m":11,"oil":9.483679,"gas":0,"water":155.7451},{"y":2026,"m":0,"oil":12.51126,"gas":0,"water":204.2341},{"y":2026,"m":1,"oil":11.27303,"gas":0,"water":181.9051},{"y":2026,"m":2,"oil":12.24516,"gas":0,"water":197.9698},{"y":2026,"m":3,"oil":25.34379,"gas":0,"water":241.3342}]