[{"y":2019,"m":0,"oil":0,"gas":0,"water":0},{"y":2019,"m":1,"oil":0,"gas":0,"water":0},{"y":2019,"m":2,"oil":0,"gas":0,"water":0},{"y":2019,"m":3,"oil":0,"gas":0,"water":0},{"y":2019,"m":4,"oil":0,"gas":0,"water":0},{"y":2019,"m":5,"oil":0,"gas":0,"water":0},{"y":2019,"m":6,"oil":0,"gas":0,"water":0},{"y":2019,"m":7,"oil":0,"gas":0,"water":0},{"y":2019,"m":8,"oil":0,"gas":0,"water":0},{"y":2019,"m":9,"oil":0,"gas":0,"water":0},{"y":2019,"m":10,"oil":0,"gas":0,"water":0},{"y":2019,"m":11,"oil":0,"gas":0,"water":0},{"y":2020,"m":0,"oil":0,"gas":0,"water":0},{"y":2020,"m":1,"oil":0,"gas":0,"water":0},{"y":2020,"m":2,"oil":0,"gas":0,"water":0},{"y":2020,"m":3,"oil":0,"gas":0,"water":0},{"y":2020,"m":4,"oil":0,"gas":0,"water":0},{"y":2020,"m":5,"oil":0,"gas":0,"water":0},{"y":2020,"m":6,"oil":0,"gas":0,"water":0},{"y":2020,"m":7,"oil":0,"gas":0,"water":0},{"y":2020,"m":8,"oil":0,"gas":0,"water":0},{"y":2020,"m":9,"oil":0,"gas":0,"water":0},{"y":2020,"m":10,"oil":0,"gas":0,"water":0},{"y":2020,"m":11,"oil":0,"gas":0,"water":0},{"y":2021,"m":0,"oil":0,"gas":0,"water":0},{"y":2021,"m":1,"oil":0,"gas":0,"water":0},{"y":2021,"m":2,"oil":0,"gas":0,"water":0},{"y":2021,"m":3,"oil":0,"gas":0,"water":0},{"y":2021,"m":4,"oil":0,"gas":0,"water":0},{"y":2021,"m":5,"oil":0,"gas":0,"water":0},{"y":2021,"m":6,"oil":0,"gas":0,"water":0},{"y":2021,"m":7,"oil":0,"gas":0,"water":0},{"y":2021,"m":8,"oil":0,"gas":0,"water":0},{"y":2021,"m":9,"oil":0,"gas":0,"water":0},{"y":2021,"m":10,"oil":0,"gas":0,"water":0},{"y":2021,"m":11,"oil":0,"gas":0,"water":0},{"y":2022,"m":0,"oil":0,"gas":0,"water":0},{"y":2022,"m":1,"oil":0,"gas":62.75585,"water":0},{"y":2022,"m":2,"oil":0,"gas":32.33099,"water":0},{"y":2022,"m":3,"oil":0,"gas":33.61838,"water":0},{"y":2022,"m":4,"oil":0,"gas":20.20702,"water":0},{"y":2022,"m":5,"oil":0,"gas":14.54109,"water":0},{"y":2022,"m":6,"oil":0,"gas":21.62475,"water":0},{"y":2022,"m":7,"oil":0,"gas":24.20668,"water":0},{"y":2022,"m":8,"oil":0,"gas":20.57554,"water":0},{"y":2022,"m":9,"oil":0,"gas":18.17715,"water":0},{"y":2022,"m":10,"oil":0,"gas":16.99412,"water":0},{"y":2022,"m":11,"oil":0,"gas":14.69647,"water":0},{"y":2023,"m":0,"oil":0,"gas":12.96982,"water":0},{"y":2023,"m":1,"oil":0,"gas":15.73864,"water":0},{"y":2023,"m":2,"oil":0,"gas":8.605158,"water":0},{"y":2023,"m":3,"oil":0,"gas":2.995678,"water":0},{"y":2023,"m":4,"oil":0,"gas":0,"water":0},{"y":2023,"m":5,"oil":0,"gas":0,"water":0},{"y":2023,"m":6,"oil":0,"gas":0,"water":0},{"y":2023,"m":7,"oil":0,"gas":4.843655,"water":0},{"y":2023,"m":8,"oil":0,"gas":19.04383,"water":0},{"y":2023,"m":9,"oil":0,"gas":17.05773,"water":0},{"y":2023,"m":10,"oil":0,"gas":24.75858,"water":0},{"y":2023,"m":11,"oil":0,"gas":36.32771,"water":0},{"y":2024,"m":0,"oil":0,"gas":37.54542,"water":0},{"y":2024,"m":1,"oil":0,"gas":29.41312,"water":0},{"y":2024,"m":2,"oil":0,"gas":37.43253,"water":0},{"y":2024,"m":3,"oil":0,"gas":27.09206,"water":0},{"y":2024,"m":4,"oil":0,"gas":20.67409,"water":0},{"y":2024,"m":5,"oil":0,"gas":18.41521,"water":0},{"y":2024,"m":6,"oil":0,"gas":29.67519,"water":0},{"y":2024,"m":7,"oil":0,"gas":16.60616,"water":0},{"y":2024,"m":8,"oil":0,"gas":10.49082,"water":0},{"y":2024,"m":9,"oil":0,"gas":22.0514,"water":0},{"y":2024,"m":10,"oil":0,"gas":19.84717,"water":0},{"y":2024,"m":11,"oil":0,"gas":15.21076,"water":0},{"y":2025,"m":0,"oil":0,"gas":12.24813,"water":0},{"y":2025,"m":1,"oil":0,"gas":9.895086,"water":0},{"y":2025,"m":2,"oil":0,"gas":14.46932,"water":0},{"y":2025,"m":3,"oil":0,"gas":12.98913,"water":0},{"y":2025,"m":4,"oil":0,"gas":17.32072,"water":0},{"y":2025,"m":5,"oil":0,"gas":20.95824,"water":0},{"y":2025,"m":6,"oil":0,"gas":8.825316,"water":0},{"y":2025,"m":7,"oil":0,"gas":23.21396,"water":0},{"y":2025,"m":8,"oil":0,"gas":14.75759,"water":0},{"y":2025,"m":9,"oil":0,"gas":14.91787,"water":0},{"y":2025,"m":10,"oil":0,"gas":11.56734,"water":0},{"y":2025,"m":11,"oil":0,"gas":9.657866,"water":0},{"y":2026,"m":0,"oil":0,"gas":9.217693,"water":0},{"y":2026,"m":1,"oil":0,"gas":9.080054,"water":0},{"y":2026,"m":2,"oil":0,"gas":44.6269,"water":0},{"y":2026,"m":3,"oil":0,"gas":18.66842,"water":0}]