[{"y":2019,"m":0,"oil":22.09,"gas":15.32,"water":22.13},{"y":2019,"m":1,"oil":18.75,"gas":17.39,"water":19.85},{"y":2019,"m":2,"oil":26.03,"gas":22.78,"water":23.98},{"y":2019,"m":3,"oil":27.97,"gas":31.75,"water":23.14},{"y":2019,"m":4,"oil":49.85,"gas":44.04,"water":22.37},{"y":2019,"m":5,"oil":40.62,"gas":32.56,"water":29.12},{"y":2019,"m":6,"oil":48.88,"gas":53.46,"water":9.24},{"y":2019,"m":7,"oil":53.89,"gas":50.95,"water":8.66},{"y":2019,"m":8,"oil":53.12,"gas":48.14,"water":10.24},{"y":2019,"m":9,"oil":57.58,"gas":58.13,"water":18.95},{"y":2019,"m":10,"oil":52.58,"gas":48.24,"water":20.17},{"y":2019,"m":11,"oil":50.59,"gas":65.87,"water":20},{"y":2020,"m":0,"oil":53.44,"gas":72.98,"water":21.02},{"y":2020,"m":1,"oil":47.53,"gas":65.61,"water":19.75},{"y":2020,"m":2,"oil":49,"gas":50.02,"water":20.03},{"y":2020,"m":3,"oil":46.85,"gas":64.25,"water":17.87},{"y":2020,"m":4,"oil":45.51,"gas":76.17,"water":17.01},{"y":2020,"m":5,"oil":43.93,"gas":74.93,"water":16.87},{"y":2020,"m":6,"oil":22.38,"gas":31.53,"water":20.28},{"y":2020,"m":7,"oil":8.2,"gas":1.54,"water":22.2},{"y":2020,"m":8,"oil":7.68,"gas":1.03,"water":22.21},{"y":2020,"m":9,"oil":7.61,"gas":0.73,"water":22.55},{"y":2020,"m":10,"oil":7.17,"gas":0.33,"water":22.18},{"y":2020,"m":11,"oil":6.71,"gas":0.18,"water":23.1},{"y":2021,"m":0,"oil":2.89,"gas":0.23,"water":12.22},{"y":2021,"m":1,"oil":2.95,"gas":0.14,"water":8.9},{"y":2021,"m":2,"oil":4.27,"gas":0,"water":1.29},{"y":2021,"m":3,"oil":0.8,"gas":0,"water":0.2},{"y":2021,"m":4,"oil":0,"gas":0,"water":0},{"y":2021,"m":5,"oil":0,"gas":0,"water":0},{"y":2021,"m":6,"oil":0,"gas":0,"water":0},{"y":2021,"m":7,"oil":0,"gas":0,"water":0},{"y":2021,"m":8,"oil":0,"gas":0,"water":0},{"y":2021,"m":9,"oil":0,"gas":0,"water":0},{"y":2021,"m":10,"oil":0,"gas":0,"water":0},{"y":2021,"m":11,"oil":0,"gas":0,"water":0},{"y":2022,"m":0,"oil":0,"gas":0,"water":0},{"y":2022,"m":1,"oil":0,"gas":0,"water":0},{"y":2022,"m":2,"oil":0,"gas":0,"water":0},{"y":2022,"m":3,"oil":0,"gas":0,"water":0},{"y":2022,"m":4,"oil":0,"gas":0,"water":0},{"y":2022,"m":5,"oil":0,"gas":0,"water":0},{"y":2022,"m":6,"oil":0,"gas":0,"water":0},{"y":2022,"m":7,"oil":0,"gas":0,"water":0},{"y":2022,"m":8,"oil":0,"gas":0,"water":0},{"y":2022,"m":9,"oil":0,"gas":0,"water":0},{"y":2022,"m":10,"oil":0,"gas":0,"water":0},{"y":2022,"m":11,"oil":0,"gas":0,"water":0},{"y":2023,"m":0,"oil":0,"gas":0,"water":0},{"y":2023,"m":1,"oil":0,"gas":0,"water":0},{"y":2023,"m":2,"oil":0,"gas":0,"water":0},{"y":2023,"m":3,"oil":0,"gas":0,"water":0},{"y":2023,"m":4,"oil":0,"gas":0,"water":0},{"y":2023,"m":5,"oil":0,"gas":0,"water":0},{"y":2023,"m":6,"oil":0,"gas":0,"water":0},{"y":2023,"m":7,"oil":0,"gas":0,"water":0},{"y":2023,"m":8,"oil":0,"gas":0,"water":0},{"y":2023,"m":9,"oil":0,"gas":0,"water":0},{"y":2023,"m":10,"oil":0,"gas":0,"water":0},{"y":2023,"m":11,"oil":0,"gas":0,"water":0},{"y":2024,"m":0,"oil":0,"gas":0,"water":0},{"y":2024,"m":1,"oil":0,"gas":0,"water":0},{"y":2024,"m":2,"oil":0,"gas":0,"water":0},{"y":2024,"m":3,"oil":0,"gas":0,"water":0},{"y":2024,"m":4,"oil":0,"gas":0,"water":0},{"y":2024,"m":5,"oil":0,"gas":0,"water":0},{"y":2024,"m":6,"oil":0,"gas":0,"water":0},{"y":2024,"m":7,"oil":0,"gas":0,"water":0},{"y":2024,"m":8,"oil":0,"gas":0,"water":0},{"y":2024,"m":9,"oil":0,"gas":0,"water":0},{"y":2024,"m":10,"oil":0,"gas":0,"water":0},{"y":2024,"m":11,"oil":0,"gas":0,"water":0},{"y":2025,"m":0,"oil":0,"gas":0,"water":0},{"y":2025,"m":1,"oil":0,"gas":0,"water":0},{"y":2025,"m":2,"oil":0,"gas":0,"water":0},{"y":2025,"m":3,"oil":0,"gas":0,"water":0},{"y":2025,"m":4,"oil":0,"gas":0,"water":0},{"y":2025,"m":5,"oil":0,"gas":0,"water":0},{"y":2025,"m":6,"oil":0,"gas":0,"water":0},{"y":2025,"m":7,"oil":0,"gas":0,"water":0},{"y":2025,"m":8,"oil":0,"gas":0,"water":0},{"y":2025,"m":9,"oil":0,"gas":0,"water":0},{"y":2025,"m":10,"oil":0,"gas":0,"water":0},{"y":2025,"m":11,"oil":0,"gas":0,"water":0},{"y":2026,"m":0,"oil":0,"gas":0,"water":0},{"y":2026,"m":1,"oil":0,"gas":0,"water":0},{"y":2026,"m":2,"oil":0,"gas":0,"water":0},{"y":2026,"m":3,"oil":0,"gas":0,"water":0}]