[{"y":2019,"m":0,"oil":0,"gas":495.32,"water":0},{"y":2019,"m":1,"oil":0,"gas":461.64,"water":0},{"y":2019,"m":2,"oil":0,"gas":721.36,"water":0},{"y":2019,"m":3,"oil":0,"gas":498.26,"water":0},{"y":2019,"m":4,"oil":0,"gas":377.02,"water":0},{"y":2019,"m":5,"oil":0,"gas":469.39,"water":0},{"y":2019,"m":6,"oil":0,"gas":557.61,"water":0},{"y":2019,"m":7,"oil":0,"gas":734.95,"water":0},{"y":2019,"m":8,"oil":0,"gas":761.94,"water":0},{"y":2019,"m":9,"oil":0,"gas":762.37,"water":0},{"y":2019,"m":10,"oil":0,"gas":903.83,"water":0},{"y":2019,"m":11,"oil":0,"gas":935.32,"water":0},{"y":2020,"m":0,"oil":0,"gas":903.07,"water":0},{"y":2020,"m":1,"oil":0,"gas":966.69,"water":0},{"y":2020,"m":2,"oil":0,"gas":1007.35,"water":0},{"y":2020,"m":3,"oil":0,"gas":975.39,"water":0},{"y":2020,"m":4,"oil":0,"gas":835.06,"water":0},{"y":2020,"m":5,"oil":0,"gas":748.2,"water":0},{"y":2020,"m":6,"oil":0,"gas":669.77,"water":0},{"y":2020,"m":7,"oil":0,"gas":644.19,"water":0},{"y":2020,"m":8,"oil":0,"gas":634.49,"water":0},{"y":2020,"m":9,"oil":0,"gas":590.9,"water":0},{"y":2020,"m":10,"oil":0,"gas":589.84,"water":0},{"y":2020,"m":11,"oil":0,"gas":652.15,"water":0},{"y":2021,"m":0,"oil":0,"gas":649.81,"water":0},{"y":2021,"m":1,"oil":0,"gas":605.22,"water":0},{"y":2021,"m":2,"oil":0,"gas":649.87,"water":0},{"y":2021,"m":3,"oil":0,"gas":559.91,"water":0},{"y":2021,"m":4,"oil":0,"gas":531.95,"water":0},{"y":2021,"m":5,"oil":0,"gas":585.21,"water":0},{"y":2021,"m":6,"oil":0,"gas":353.09,"water":0},{"y":2021,"m":7,"oil":0,"gas":325.09,"water":0},{"y":2021,"m":8,"oil":0,"gas":287.15,"water":0},{"y":2021,"m":9,"oil":0,"gas":332.17,"water":0},{"y":2021,"m":10,"oil":0,"gas":294.58,"water":0},{"y":2021,"m":11,"oil":0,"gas":284.44,"water":0},{"y":2022,"m":0,"oil":0,"gas":280.46,"water":0},{"y":2022,"m":1,"oil":0,"gas":282.1,"water":0},{"y":2022,"m":2,"oil":0,"gas":324.12,"water":0},{"y":2022,"m":3,"oil":0,"gas":232.65,"water":0},{"y":2022,"m":4,"oil":0,"gas":70.67,"water":0},{"y":2022,"m":5,"oil":0,"gas":73.7,"water":0},{"y":2022,"m":6,"oil":0,"gas":80.99,"water":0},{"y":2022,"m":7,"oil":0,"gas":17.18,"water":0},{"y":2022,"m":8,"oil":0,"gas":0,"water":0},{"y":2022,"m":9,"oil":0,"gas":0,"water":0},{"y":2022,"m":10,"oil":0,"gas":0,"water":0},{"y":2022,"m":11,"oil":0,"gas":0,"water":0},{"y":2023,"m":0,"oil":0,"gas":0,"water":0},{"y":2023,"m":1,"oil":0,"gas":0,"water":0},{"y":2023,"m":2,"oil":0,"gas":0,"water":0},{"y":2023,"m":3,"oil":0,"gas":0,"water":0},{"y":2023,"m":4,"oil":0,"gas":0,"water":0},{"y":2023,"m":5,"oil":0,"gas":0,"water":0},{"y":2023,"m":6,"oil":0,"gas":0,"water":0},{"y":2023,"m":7,"oil":0,"gas":0,"water":0},{"y":2023,"m":8,"oil":0,"gas":0,"water":0},{"y":2023,"m":9,"oil":0,"gas":0,"water":0},{"y":2023,"m":10,"oil":0,"gas":0,"water":0},{"y":2023,"m":11,"oil":0,"gas":0,"water":0},{"y":2024,"m":0,"oil":0,"gas":0,"water":0},{"y":2024,"m":1,"oil":0,"gas":0,"water":0},{"y":2024,"m":2,"oil":0,"gas":0,"water":0},{"y":2024,"m":3,"oil":0,"gas":0,"water":0},{"y":2024,"m":4,"oil":0,"gas":0,"water":0},{"y":2024,"m":5,"oil":0,"gas":0,"water":0},{"y":2024,"m":6,"oil":0,"gas":0,"water":0},{"y":2024,"m":7,"oil":0,"gas":0,"water":0},{"y":2024,"m":8,"oil":0,"gas":0,"water":0},{"y":2024,"m":9,"oil":0,"gas":0,"water":0},{"y":2024,"m":10,"oil":0,"gas":0,"water":0},{"y":2024,"m":11,"oil":0,"gas":0,"water":0},{"y":2025,"m":0,"oil":0,"gas":0,"water":0},{"y":2025,"m":1,"oil":0,"gas":0,"water":0},{"y":2025,"m":2,"oil":0,"gas":0,"water":0},{"y":2025,"m":3,"oil":0,"gas":0,"water":0},{"y":2025,"m":4,"oil":0,"gas":0,"water":0},{"y":2025,"m":5,"oil":0,"gas":0,"water":0},{"y":2025,"m":6,"oil":0,"gas":0,"water":0},{"y":2025,"m":7,"oil":0,"gas":0,"water":0},{"y":2025,"m":8,"oil":0,"gas":0,"water":0},{"y":2025,"m":9,"oil":0,"gas":0,"water":0},{"y":2025,"m":10,"oil":0,"gas":0,"water":0},{"y":2025,"m":11,"oil":0,"gas":0,"water":0},{"y":2026,"m":0,"oil":0,"gas":0,"water":0},{"y":2026,"m":1,"oil":0,"gas":0,"water":0},{"y":2026,"m":2,"oil":0,"gas":0,"water":0},{"y":2026,"m":3,"oil":0,"gas":0,"water":0}]