[{"y":2019,"m":0,"oil":0,"gas":0,"water":0},{"y":2019,"m":1,"oil":0,"gas":0,"water":0},{"y":2019,"m":2,"oil":0,"gas":0,"water":0},{"y":2019,"m":3,"oil":0,"gas":0,"water":0},{"y":2019,"m":4,"oil":0,"gas":0,"water":0},{"y":2019,"m":5,"oil":0,"gas":0,"water":0},{"y":2019,"m":6,"oil":0,"gas":0,"water":0},{"y":2019,"m":7,"oil":0,"gas":0,"water":0},{"y":2019,"m":8,"oil":0,"gas":0,"water":0},{"y":2019,"m":9,"oil":0,"gas":0,"water":0},{"y":2019,"m":10,"oil":0,"gas":0,"water":0},{"y":2019,"m":11,"oil":0,"gas":0,"water":0},{"y":2020,"m":0,"oil":0,"gas":0,"water":0},{"y":2020,"m":1,"oil":12.26,"gas":0.18,"water":80.3},{"y":2020,"m":2,"oil":114.27,"gas":3.33,"water":709.61},{"y":2020,"m":3,"oil":105.28,"gas":1.84,"water":703.62},{"y":2020,"m":4,"oil":101.01,"gas":3.07,"water":428.82},{"y":2020,"m":5,"oil":92.39,"gas":2.13,"water":387.68},{"y":2020,"m":6,"oil":88,"gas":2.03,"water":375.83},{"y":2020,"m":7,"oil":79.76,"gas":1.34,"water":366.7},{"y":2020,"m":8,"oil":59.37,"gas":1.08,"water":356.78},{"y":2020,"m":9,"oil":41.21,"gas":1.43,"water":356.42},{"y":2020,"m":10,"oil":47.6,"gas":1.12,"water":400.18},{"y":2020,"m":11,"oil":66.76,"gas":1.11,"water":430.15},{"y":2021,"m":0,"oil":77.86,"gas":0.19,"water":424.5},{"y":2021,"m":1,"oil":73.67,"gas":2.22,"water":353.49},{"y":2021,"m":2,"oil":72.69,"gas":2.09,"water":522.91},{"y":2021,"m":3,"oil":64.07,"gas":2.21,"water":403.58},{"y":2021,"m":4,"oil":67.33,"gas":0.97,"water":423.36},{"y":2021,"m":5,"oil":73.06,"gas":0.55,"water":499.64},{"y":2021,"m":6,"oil":78.07,"gas":1.63,"water":500.73},{"y":2021,"m":7,"oil":69.92,"gas":1.1,"water":540.71},{"y":2021,"m":8,"oil":27.92,"gas":0.54,"water":237.93},{"y":2021,"m":9,"oil":56.18,"gas":2.06,"water":484.85},{"y":2021,"m":10,"oil":53.75,"gas":2.45,"water":605.95},{"y":2021,"m":11,"oil":39.44,"gas":2.42,"water":634.83},{"y":2022,"m":0,"oil":40.6,"gas":1.06,"water":652.24},{"y":2022,"m":1,"oil":36.91,"gas":0.79,"water":569.6},{"y":2022,"m":2,"oil":108.56,"gas":2.49,"water":647.45},{"y":2022,"m":3,"oil":132.24,"gas":2.51,"water":637.87},{"y":2022,"m":4,"oil":130.22,"gas":3.15,"water":607.62},{"y":2022,"m":5,"oil":143.19,"gas":0.6,"water":503.41},{"y":2022,"m":6,"oil":134.46,"gas":11.96,"water":484.93},{"y":2022,"m":7,"oil":119.27,"gas":9.67,"water":437.56},{"y":2022,"m":8,"oil":110.53,"gas":12.69,"water":435.98},{"y":2022,"m":9,"oil":100.65,"gas":7.48,"water":388.09},{"y":2022,"m":10,"oil":101.42,"gas":0.79,"water":398.4},{"y":2022,"m":11,"oil":118.47,"gas":0.87,"water":455.1},{"y":2023,"m":0,"oil":112.97,"gas":0.82,"water":457.99},{"y":2023,"m":1,"oil":82.05,"gas":0.63,"water":416.14},{"y":2023,"m":2,"oil":94.24,"gas":0.48,"water":447.28},{"y":2023,"m":3,"oil":108.02,"gas":0,"water":434.09},{"y":2023,"m":4,"oil":101.4,"gas":0,"water":491.16},{"y":2023,"m":5,"oil":95.76,"gas":0,"water":471.94},{"y":2023,"m":6,"oil":98.37,"gas":0,"water":491.03},{"y":2023,"m":7,"oil":87.59,"gas":0,"water":508.65},{"y":2023,"m":8,"oil":84.15,"gas":0,"water":485.48},{"y":2023,"m":9,"oil":81.33,"gas":0,"water":542.41},{"y":2023,"m":10,"oil":87.21,"gas":0,"water":532.31},{"y":2023,"m":11,"oil":130.12,"gas":0,"water":534.56},{"y":2024,"m":0,"oil":129.38,"gas":0,"water":575.48},{"y":2024,"m":1,"oil":92.74,"gas":0,"water":539.52},{"y":2024,"m":2,"oil":99.24,"gas":0,"water":552.42},{"y":2024,"m":3,"oil":99.62,"gas":0,"water":460.89},{"y":2024,"m":4,"oil":89.83,"gas":0,"water":517.2},{"y":2024,"m":5,"oil":72.64,"gas":0,"water":466.01},{"y":2024,"m":6,"oil":79.95,"gas":0,"water":439.98},{"y":2024,"m":7,"oil":77.68,"gas":0,"water":427.76},{"y":2024,"m":8,"oil":71.29,"gas":0,"water":551.76},{"y":2024,"m":9,"oil":66.71,"gas":0,"water":586.85},{"y":2024,"m":10,"oil":66.03,"gas":0,"water":605.13},{"y":2024,"m":11,"oil":66.32,"gas":0,"water":617.15},{"y":2025,"m":0,"oil":72.7,"gas":0,"water":574.39},{"y":2025,"m":1,"oil":63.92,"gas":0,"water":511.02},{"y":2025,"m":2,"oil":69.16,"gas":0,"water":673.76},{"y":2025,"m":3,"oil":58.63,"gas":0,"water":630.44},{"y":2025,"m":4,"oil":69.17,"gas":0,"water":610.55},{"y":2025,"m":5,"oil":65.24,"gas":0,"water":564.61},{"y":2025,"m":6,"oil":66.77,"gas":0,"water":544.09},{"y":2025,"m":7,"oil":73.08,"gas":0,"water":507.1},{"y":2025,"m":8,"oil":67.7,"gas":0,"water":441.16},{"y":2025,"m":9,"oil":70.02,"gas":0,"water":533.5},{"y":2025,"m":10,"oil":69.7,"gas":0,"water":627.53},{"y":2025,"m":11,"oil":88.93064,"gas":0,"water":633.0187},{"y":2026,"m":0,"oil":91.5275,"gas":0,"water":640.4792},{"y":2026,"m":1,"oil":45.30046,"gas":0,"water":587.601},{"y":2026,"m":2,"oil":47.5439,"gas":0,"water":642.3895},{"y":2026,"m":3,"oil":41.04164,"gas":0,"water":663.3141}]